Workbook
Name DEN: CONVERTER!$D$1

Sheet ASSUMPTION
A1: Period of Construction of restaurant – 3 Months.
A3: Start of Construction | G3: 43922
A4: Construction period | G4: 3 Months
A5: Date of Operations | G5: =EOMONTH(G3,2)+1 -> 44013
A6: Revenue
A8: Particulars | B8: Weekdays | C8: Weekend | E8: Particulars | F8: Weekdays | G8: Weekend
A9: Lunch | E9: Dinner
A10: APC | B10: =SUBTOTAL(9,B11:B13) -> 1500 | C10: =SUBTOTAL(9,C11:C13) -> 1700 | E10: APC | F10: =SUBTOTAL(9,F11:F13) -> 1600 | G10: =SUBTOTAL(9,G11:G13) -> 1900
A11: Alcoholic Beverages | B11: 300 | C11: 500 | E11: Alcoholic Beverages | F11: 400 | G11: 650
A12: Non Alcoholic Beverages | B12: 200 | C12: 200 | E12: Non Alcoholic Beverages | F12: 200 | G12: 250
A13: Food | B13: 1000 | C13: 1000 | E13: Food | F13: 1000 | G13: 1000
A14: Y-O-Y Growth price rate | B14: 0.05 | C14: 0.05 | E14: Y-O-Y Price Growth rate | F14: 0.05 | G14: 0.05
A16: Occupancy | E16: Occupancy
A17: Number of Covers Available | B17: 100 | C17: 100 | E17: Number of Covers Available | F17: 100 | G17: 100
A18: Number of Rounds Available | B18: 2 | C18: 2 | E18: Number of Rounds Available | F18: 2 | G18: 2
A19: Number of Covers Occupied/ Round | B19: 10 | C19: 13 | E19: Number of Covers Occupied/ Round | F19: 13 | G19: 15
A20: MoM growth | B20: 0.02 | C20: 0.04 | E20: MoM growth | F20: 0.02 | G20: 0.04
A21: Maximum Occupancy/Round | B21: 60 | C21: 80 | E21: Maximum Occupancy/Round | F21: 70 | G21: 90
A24: Direct Expenses
A25: Alcoholic Beverage cost (% of revenue) | G25: 0.35
A26: Non Alcoholic Beverages (% of revenue) | G26: 0.4
A27: Food (% of revenue) | G27: 0.3
A29: Salary
A30: Members of Team | E30: Number of Employees | F30: Salary / M | G30: Salary / M
A31: Receptionist | E31: 2 | F31: 20000 | G31: 40000
A32: Restaurants Manager | E32: 2 | F32: 50000 | G32: 100000
A33: Waiters | E33: 10 | F33: 20000 | G33: 200000
A34: Head Chef | E34: 1 | F34: 100000 | G34: 100000
A35: Chefs | E35: 2 | F35: 75000 | G35: 150000
A36: Assistant Chef | E36: 6 | F36: 30000 | G36: 180000
A37: Valet Parking | E37: 3 | F37: 17000 | G37: 51000
A38: Cleaners | E38: 5 | F38: 17000 | G38: 85000
A39: Bartender | E39: 4 | F39: 20000 | G39: 80000
A40: Total | G40: =SUM(G31:G39) -> 986000
A41: Staff salary will increase Y-o-Y basis | G41: 0.08
A42: Indirect Expenses
A43: Members of Team | E43: Number of Employees | F43: Salary / M | G43: Salary / M
A44: HR Manager | E44: 1 | F44: 50000 | G44: 50000
A45: Assistant Manager | E45: 2 | F45: 35000 | G45: 70000
A46: Security | E46: 2 | F46: 20000 | G46: 40000
A47: Purchase Manager | E47: 2 | F47: 40000 | G47: 80000
A48: Accountant | E48: 2 | F48: 40000 | G48: 80000
A49: Others | E49: 2 | F49: 30000 | G49: 60000
A50: Total | G50: =SUM(G44:G49) -> 380000
A52: Rotalty to brand (% Of Revenue) | G52: 0.05
A53: Rent (as per contract) (% of revenue) | G53: 0.1
A54: Water Cost (per month) | G54: 10000
A55: Maintenance (per month) | G55: 50000
A56: Marketing cost (per month) | G56: 25000
A57: Electricity (Based on area Rs./sq. Ft.) | G57: 5
A58: Phone and internet (per month) | G58: 15000
A59: Housekeeping & Consumables (% of revenue) | G59: 0.02
A60: Payment Settlement Charges (% or revenue) | G60: 0.015
A61: Numbers of Tables occupied opting for card payment | G61: 0.5
A62: Indirect expenses will increase Y-o-Y basis | G62: 0.08
A64: Area specifications
A65: Carpet Area required (Sq. ft.) | G65: 4000
A66: Conversion Rate | G66: 1.33 | J66: =G67*G57 -> 26600
A67: Super Built up area to be rented (Sq. ft.) | G67: =G65*G66 -> 5320
A68: Serving Area (% of carpet area) | G68: 0.75
A69: Serving Area | G69: 3000
A70: Kitchen Area | G70: 1000
A71: Area per cover (Sq.Ft.) | G71: 25
A72: Covers | G72: 100
A73: Sitting per table | G73: 4
A74: Number of Tables | G74: 30
A77: Capital Expenditure
A78: Equipments | G78: Rate per Sq Ft
A79: Kitchen Equipments and cutlery | G79: 3000
A80: Refrigeration Equipments | G80: 5000
A81: Furniture & Fixtures | G81: 1700
A82: Restaurants Décor | G82: 2000
A83: Rent Deposits | G83: 1000000
A85: Working capital
G86: Days
A87: Initial working capital introduced | G87: =2400000 -> 2400000
A88: Inventory
A89: Alcoholic Beverages | G89: 30
A90: Non-Alcoholic Beverages | G90: 15
A91: Food | G91: 5
A92: Creditor For Raw material | G92: 30
A93: Creditor For Expenses | G93: 30
A95: Depreciation
A96: Equipments | G96: 0.15
A97: Furniture & Fixtures and Restaurant décor | G97: 0.1
A99: Capital Structure
A100: Equity | G100: 1
A101: Debt | G101: =G100-1 -> 0
A102: Cash credit limit will be availed if required
A103: Rate of Interest on CC Limit | G103: 0.12
A105: Tax Rate | G105: 0.2517
A107: End of sheet

Sheet CONVERTER
A1: CURRENCY IN INR | B1: Model in | C1: LAKHS | D1: =VLOOKUP(C1,$A$3:$B$9,2,) -> 100000
A3: ONES | B3: 1
A4: TENS | B4: 10
A5: HUNDREDS | B5: 100
A6: THOUSANDS | B6: 1000
A7: LAKHS | B7: 100000
A8: MILLIONS | B8: 1000000
A9: CRORES | B9: 10000000

Sheet MONTHLY REVENUE
A1: ALL FINAL VALUES IN | B1: =CONVERTER!C1 -> LAKHS
E7: 0 | F7: 1 | G7: =F7+1 -> 2 | H7: =G7+1 -> 3 | I7: =H7+1 -> 4 | J7: =I7+1 -> 5 | K7: =J7+1 -> 6 | L7: =K7+1 -> 7 | M7: =L7+1 -> 8 | N7: =M7+1 -> 9 | ... AO7: =AN7+1 -> 36
F8: =EOMONTH(ASSUMPTION!G3,0) -> 43951 | G8: =EOMONTH(F8,1) -> 43982 | H8: =EOMONTH(G8,1) -> 44012 | I8: =EOMONTH(H8,1) -> 44043 | J8: =EOMONTH(I8,1) -> 44074 | K8: =EOMONTH(J8,1) -> 44104 | L8: =EOMONTH(K8,1) -> 44135 | M8: =EOMONTH(L8,1) -> 44165 | N8: =EOMONTH(M8,1) -> 44196 | ... AO8: =EOMONTH(AN8,1) -> 45016
A9: OPERATING DAYS | F9: =IF(F8>ASSUMPTION!$G$5,DAY('MONTHLY REVENUE'!F8),0) -> 0 | G9: =IF(G8>ASSUMPTION!$G$5,DAY('MONTHLY REVENUE'!G8),0) -> 0 | H9: =IF(H8>ASSUMPTION!$G$5,DAY('MONTHLY REVENUE'!H8),0) -> 0 | I9: =IF(I8>ASSUMPTION!$G$5,DAY('MONTHLY REVENUE'!I8),0) -> 31 | J9: =IF(J8>ASSUMPTION!$G$5,DAY('MONTHLY REVENUE'!J8),0) -> 31 | K9: =IF(K8>ASSUMPTION!$G$5,DAY('MONTHLY REVENUE'!K8),0) -> 30 | L9: =IF(L8>ASSUMPTION!$G$5,DAY('MONTHLY REVENUE'!L8),0) -> 31 | M9: =IF(M8>ASSUMPTION!$G$5,DAY('MONTHLY REVENUE'!M8),0) -> 30 | ... AO9: =IF(AO8>ASSUMPTION!$G$5,DAY('MONTHLY REVENUE'!AO8),0) -> 31
A10: NO OF WEEKDAYS IN THE MONTH | F10: =IF(F9>0,NETWORKDAYS(E8+1,F8),0) -> 0 | G10: =IF(G9>0,NETWORKDAYS(F8+1,G8),0) -> 0 | H10: =IF(H9>0,NETWORKDAYS(G8+1,H8),0) -> 0 | I10: =IF(I9>0,NETWORKDAYS(H8+1,I8),0) -> 23 | J10: =IF(J9>0,NETWORKDAYS(I8+1,J8),0) -> 21 | K10: =IF(K9>0,NETWORKDAYS(J8+1,K8),0) -> 22 | L10: =IF(L9>0,NETWORKDAYS(K8+1,L8),0) -> 22 | M10: =IF(M9>0,NETWORKDAYS(L8+1,M8),0) -> 21 | ... AO10: =IF(AO9>0,NETWORKDAYS(AN8+1,AO8),0) -> 23
A11: NO OF WEEKENDS IN THE MONTH | G11: =G9-G10 -> 0 | H11: =H9-H10 -> 0 | I11: =I9-I10 -> 8 | J11: =J9-J10 -> 10 | K11: =K9-K10 -> 8 | L11: =L9-L10 -> 9 | M11: =M9-M10 -> 9 | N11: =N9-N10 -> 8 | ... AO11: =AO9-AO10 -> 8
A13: NO OF GUESTS PER DAY
A14: WEEKDAYS | K14: =IF('MONTHLY REVENUE'!G$9>0,MIN(MAX(ASSUMPTION!$B$19*ASSUMPTION!$B$18,'MONTHLY REVENUE'!F$9*(1+ASSUMPTION!$A$20)),ASSUMPTION!$B$21),0) -> 0
A15: LUNCH | F15: =IF(F$9>0,MIN(MAX(ASSUMPTION!$B$19*ASSUMPTION!$B$18,'MONTHLY REVENUE'!E15*(1+ASSUMPTION!$B$20)),ASSUMPTION!$B$21),0) -> 0 | G15: =IF(G$9>0,MIN(MAX(ASSUMPTION!$B$19*ASSUMPTION!$B$18,'MONTHLY REVENUE'!F15*(1+ASSUMPTION!$B$20)),ASSUMPTION!$B$21),0) -> 0 | H15: =IF(H$9>0,MIN(MAX(ASSUMPTION!$B$19*ASSUMPTION!$B$18,'MONTHLY REVENUE'!G15*(1+ASSUMPTION!$B$20)),ASSUMPTION!$B$21),0) -> 0 | I15: =IF(I$9>0,MIN(MAX(ASSUMPTION!$B$19*ASSUMPTION!$B$18,'MONTHLY REVENUE'!H15*(1+ASSUMPTION!$B$20)),ASSUMPTION!$B$21),0) -> 20 | J15: =IF(J$9>0,MIN(MAX(ASSUMPTION!$B$19*ASSUMPTION!$B$18,'MONTHLY REVENUE'!I15*(1+ASSUMPTION!$B$20)),ASSUMPTION!$B$21),0) -> 20.4 | K15: =IF(K$9>0,MIN(MAX(ASSUMPTION!$B$19*ASSUMPTION!$B$18,'MONTHLY REVENUE'!J15*(1+ASSUMPTION!$B$20)),ASSUMPTION!$B$21),0) -> 20.808 | L15: =IF(L$9>0,MIN(MAX(ASSUMPTION!$B$19*ASSUMPTION!$B$18,'MONTHLY REVENUE'!K15*(1+ASSUMPTION!$B$20)),ASSUMPTION!$B$21),0) -> 21.22416 | M15: =IF(M$9>0,MIN(MAX(ASSUMPTION!$B$19*ASSUMPTION!$B$18,'MONTHLY REVENUE'!L15*(1+ASSUMPTION!$B$20)),ASSUMPTION!$B$21),0) -> 21.648643 | ... AO15: =IF(AO$9>0,MIN(MAX(ASSUMPTION!$B$19*ASSUMPTION!$B$18,'MONTHLY REVENUE'!AN15*(1+ASSUMPTION!$B$20)),ASSUMPTION!$B$21),0) -> 37.690812
A16: DINNER | F16: =IF(F$9>0,MIN(MAX(ASSUMPTION!$F$19*ASSUMPTION!$F$18,'MONTHLY REVENUE'!E16*(1+ASSUMPTION!$F$20)),ASSUMPTION!$F$21),0) -> 0 | G16: =IF(G$9>0,MIN(MAX(ASSUMPTION!$F$19*ASSUMPTION!$F$18,'MONTHLY REVENUE'!F16*(1+ASSUMPTION!$F$20)),ASSUMPTION!$F$21),0) -> 0 | H16: =IF(H$9>0,MIN(MAX(ASSUMPTION!$F$19*ASSUMPTION!$F$18,'MONTHLY REVENUE'!G16*(1+ASSUMPTION!$F$20)),ASSUMPTION!$F$21),0) -> 0 | I16: =IF(I$9>0,MIN(MAX(ASSUMPTION!$F$19*ASSUMPTION!$F$18,'MONTHLY REVENUE'!H16*(1+ASSUMPTION!$F$20)),ASSUMPTION!$F$21),0) -> 26 | J16: =IF(J$9>0,MIN(MAX(ASSUMPTION!$F$19*ASSUMPTION!$F$18,'MONTHLY REVENUE'!I16*(1+ASSUMPTION!$F$20)),ASSUMPTION!$F$21),0) -> 26.52 | K16: =IF(K$9>0,MIN(MAX(ASSUMPTION!$F$19*ASSUMPTION!$F$18,'MONTHLY REVENUE'!J16*(1+ASSUMPTION!$F$20)),ASSUMPTION!$F$21),0) -> 27.0504 | L16: =IF(L$9>0,MIN(MAX(ASSUMPTION!$F$19*ASSUMPTION!$F$18,'MONTHLY REVENUE'!K16*(1+ASSUMPTION!$F$20)),ASSUMPTION!$F$21),0) -> 27.591408 | M16: =IF(M$9>0,MIN(MAX(ASSUMPTION!$F$19*ASSUMPTION!$F$18,'MONTHLY REVENUE'!L16*(1+ASSUMPTION!$F$20)),ASSUMPTION!$F$21),0) -> 28.143236 | ... AO16: =IF(AO$9>0,MIN(MAX(ASSUMPTION!$F$19*ASSUMPTION!$F$18,'MONTHLY REVENUE'!AN16*(1+ASSUMPTION!$F$20)),ASSUMPTION!$F$21),0) -> 48.998055
A19: WEEKENDS
A20: LUNCH | F20: =IF(F$9>0,MIN(MAX(ASSUMPTION!$C$19*ASSUMPTION!$C$18,'MONTHLY REVENUE'!E20*(1+ASSUMPTION!$C$20)),ASSUMPTION!$C$21),0) -> 0 | G20: =IF(G$9>0,MIN(MAX(ASSUMPTION!$C$19*ASSUMPTION!$C$18,'MONTHLY REVENUE'!F20*(1+ASSUMPTION!$C$20)),ASSUMPTION!$C$21),0) -> 0 | H20: =IF(H$9>0,MIN(MAX(ASSUMPTION!$C$19*ASSUMPTION!$C$18,'MONTHLY REVENUE'!G20*(1+ASSUMPTION!$C$20)),ASSUMPTION!$C$21),0) -> 0 | I20: =IF(I$9>0,MIN(MAX(ASSUMPTION!$C$19*ASSUMPTION!$C$18,'MONTHLY REVENUE'!H20*(1+ASSUMPTION!$C$20)),ASSUMPTION!$C$21),0) -> 26 | J20: =IF(J$9>0,MIN(MAX(ASSUMPTION!$C$19*ASSUMPTION!$C$18,'MONTHLY REVENUE'!I20*(1+ASSUMPTION!$C$20)),ASSUMPTION!$C$21),0) -> 27.04 | K20: =IF(K$9>0,MIN(MAX(ASSUMPTION!$C$19*ASSUMPTION!$C$18,'MONTHLY REVENUE'!J20*(1+ASSUMPTION!$C$20)),ASSUMPTION!$C$21),0) -> 28.1216 | L20: =IF(L$9>0,MIN(MAX(ASSUMPTION!$C$19*ASSUMPTION!$C$18,'MONTHLY REVENUE'!K20*(1+ASSUMPTION!$C$20)),ASSUMPTION!$C$21),0) -> 29.246464 | M20: =IF(M$9>0,MIN(MAX(ASSUMPTION!$C$19*ASSUMPTION!$C$18,'MONTHLY REVENUE'!L20*(1+ASSUMPTION!$C$20)),ASSUMPTION!$C$21),0) -> 30.416323 | ... AO20: =IF(AO$9>0,MIN(MAX(ASSUMPTION!$C$19*ASSUMPTION!$C$18,'MONTHLY REVENUE'!AN20*(1+ASSUMPTION!$C$20)),ASSUMPTION!$C$21),0) -> 80
A21: DINNER | F21: =IF(F$9>0,MIN(MAX(ASSUMPTION!$G$19*ASSUMPTION!$G$18,'MONTHLY REVENUE'!E21*(1+ASSUMPTION!$G$20)),ASSUMPTION!$G$21),0) -> 0 | G21: =IF(G$9>0,MIN(MAX(ASSUMPTION!$G$19*ASSUMPTION!$G$18,'MONTHLY REVENUE'!F21*(1+ASSUMPTION!$G$20)),ASSUMPTION!$G$21),0) -> 0 | H21: =IF(H$9>0,MIN(MAX(ASSUMPTION!$G$19*ASSUMPTION!$G$18,'MONTHLY REVENUE'!G21*(1+ASSUMPTION!$G$20)),ASSUMPTION!$G$21),0) -> 0 | I21: =IF(I$9>0,MIN(MAX(ASSUMPTION!$G$19*ASSUMPTION!$G$18,'MONTHLY REVENUE'!H21*(1+ASSUMPTION!$G$20)),ASSUMPTION!$G$21),0) -> 30 | J21: =IF(J$9>0,MIN(MAX(ASSUMPTION!$G$19*ASSUMPTION!$G$18,'MONTHLY REVENUE'!I21*(1+ASSUMPTION!$G$20)),ASSUMPTION!$G$21),0) -> 31.2 | K21: =IF(K$9>0,MIN(MAX(ASSUMPTION!$G$19*ASSUMPTION!$G$18,'MONTHLY REVENUE'!J21*(1+ASSUMPTION!$G$20)),ASSUMPTION!$G$21),0) -> 32.448 | L21: =IF(L$9>0,MIN(MAX(ASSUMPTION!$G$19*ASSUMPTION!$G$18,'MONTHLY REVENUE'!K21*(1+ASSUMPTION!$G$20)),ASSUMPTION!$G$21),0) -> 33.74592 | M21: =IF(M$9>0,MIN(MAX(ASSUMPTION!$G$19*ASSUMPTION!$G$18,'MONTHLY REVENUE'!L21*(1+ASSUMPTION!$G$20)),ASSUMPTION!$G$21),0) -> 35.095757 | ... AO21: =IF(AO$9>0,MIN(MAX(ASSUMPTION!$G$19*ASSUMPTION!$G$18,'MONTHLY REVENUE'!AN21*(1+ASSUMPTION!$G$20)),ASSUMPTION!$G$21),0) -> 90
A23: APC
A24: WEEKDAYS
A25: LUNCH
A26: Alcoholic Beverages | F26: =IF(MOD(F$7,12)=4,MAX(E26*(1+ASSUMPTION!$B$14),ASSUMPTION!$B$11),'MONTHLY REVENUE'!E26) -> 0 | G26: =IF(MOD(G$7,12)=4,MAX(F26*(1+ASSUMPTION!$B$14),ASSUMPTION!$B$11),'MONTHLY REVENUE'!F26) -> 0 | H26: =IF(MOD(H$7,12)=4,MAX(G26*(1+ASSUMPTION!$B$14),ASSUMPTION!$B$11),'MONTHLY REVENUE'!G26) -> 0 | I26: =IF(MOD(I$7,12)=4,MAX(H26*(1+ASSUMPTION!$B$14),ASSUMPTION!$B$11),'MONTHLY REVENUE'!H26) -> 300 | J26: =IF(MOD(J$7,12)=4,MAX(I26*(1+ASSUMPTION!$B$14),ASSUMPTION!$B$11),'MONTHLY REVENUE'!I26) -> 300 | K26: =IF(MOD(K$7,12)=4,MAX(J26*(1+ASSUMPTION!$B$14),ASSUMPTION!$B$11),'MONTHLY REVENUE'!J26) -> 300 | L26: =IF(MOD(L$7,12)=4,MAX(K26*(1+ASSUMPTION!$B$14),ASSUMPTION!$B$11),'MONTHLY REVENUE'!K26) -> 300 | M26: =IF(MOD(M$7,12)=4,MAX(L26*(1+ASSUMPTION!$B$14),ASSUMPTION!$B$11),'MONTHLY REVENUE'!L26) -> 300 | ... AO26: =IF(MOD(AO$7,12)=4,MAX(AN26*(1+ASSUMPTION!$B$14),ASSUMPTION!$B$11),'MONTHLY REVENUE'!AN26) -> 330.75
A27: Non Alcoholic Beverages | F27: =IF(MOD(F$7,12)=4,MAX(E27*(1+ASSUMPTION!$B$14),ASSUMPTION!$B$12),'MONTHLY REVENUE'!E27) -> 0 | G27: =IF(MOD(G$7,12)=4,MAX(F27*(1+ASSUMPTION!$B$14),ASSUMPTION!$B$12),'MONTHLY REVENUE'!F27) -> 0 | H27: =IF(MOD(H$7,12)=4,MAX(G27*(1+ASSUMPTION!$B$14),ASSUMPTION!$B$12),'MONTHLY REVENUE'!G27) -> 0 | I27: =IF(MOD(I$7,12)=4,MAX(H27*(1+ASSUMPTION!$B$14),ASSUMPTION!$B$12),'MONTHLY REVENUE'!H27) -> 200 | J27: =IF(MOD(J$7,12)=4,MAX(I27*(1+ASSUMPTION!$B$14),ASSUMPTION!$B$12),'MONTHLY REVENUE'!I27) -> 200 | K27: =IF(MOD(K$7,12)=4,MAX(J27*(1+ASSUMPTION!$B$14),ASSUMPTION!$B$12),'MONTHLY REVENUE'!J27) -> 200 | L27: =IF(MOD(L$7,12)=4,MAX(K27*(1+ASSUMPTION!$B$14),ASSUMPTION!$B$12),'MONTHLY REVENUE'!K27) -> 200 | M27: =IF(MOD(M$7,12)=4,MAX(L27*(1+ASSUMPTION!$B$14),ASSUMPTION!$B$12),'MONTHLY REVENUE'!L27) -> 200 | ... AO27: =IF(MOD(AO$7,12)=4,MAX(AN27*(1+ASSUMPTION!$B$14),ASSUMPTION!$B$12),'MONTHLY REVENUE'!AN27) -> 220.5
A28: Food | F28: =IF(MOD(F$7,12)=4,MAX(E28*(1+ASSUMPTION!$B$14),ASSUMPTION!$B$13),'MONTHLY REVENUE'!E28) -> 0 | G28: =IF(MOD(G$7,12)=4,MAX(F28*(1+ASSUMPTION!$B$14),ASSUMPTION!$B$13),'MONTHLY REVENUE'!F28) -> 0 | H28: =IF(MOD(H$7,12)=4,MAX(G28*(1+ASSUMPTION!$B$14),ASSUMPTION!$B$13),'MONTHLY REVENUE'!G28) -> 0 | I28: =IF(MOD(I$7,12)=4,MAX(H28*(1+ASSUMPTION!$B$14),ASSUMPTION!$B$13),'MONTHLY REVENUE'!H28) -> 1000 | J28: =IF(MOD(J$7,12)=4,MAX(I28*(1+ASSUMPTION!$B$14),ASSUMPTION!$B$13),'MONTHLY REVENUE'!I28) -> 1000 | K28: =IF(MOD(K$7,12)=4,MAX(J28*(1+ASSUMPTION!$B$14),ASSUMPTION!$B$13),'MONTHLY REVENUE'!J28) -> 1000 | L28: =IF(MOD(L$7,12)=4,MAX(K28*(1+ASSUMPTION!$B$14),ASSUMPTION!$B$13),'MONTHLY REVENUE'!K28) -> 1000 | M28: =IF(MOD(M$7,12)=4,MAX(L28*(1+ASSUMPTION!$B$14),ASSUMPTION!$B$13),'MONTHLY REVENUE'!L28) -> 1000 | ... AO28: =IF(MOD(AO$7,12)=4,MAX(AN28*(1+ASSUMPTION!$B$14),ASSUMPTION!$B$13),'MONTHLY REVENUE'!AN28) -> 1102.5
A29: TOTAL | F29: =SUM(F26:F28) -> 0 | G29: =SUM(G26:G28) -> 0 | H29: =SUM(H26:H28) -> 0 | I29: =SUM(I26:I28) -> 1500 | J29: =SUM(J26:J28) -> 1500 | K29: =SUM(K26:K28) -> 1500 | L29: =SUM(L26:L28) -> 1500 | M29: =SUM(M26:M28) -> 1500 | ... AO29: =SUM(AO26:AO28) -> 1653.75
A31: DINNER
A32: Alcoholic Beverages | F32: =IF(MOD(F$7,12)=4,MAX(E32*(1+ASSUMPTION!$F$14),ASSUMPTION!$F$11),'MONTHLY REVENUE'!E32) -> 0 | G32: =IF(MOD(G$7,12)=4,MAX(F32*(1+ASSUMPTION!$F$14),ASSUMPTION!$F$11),'MONTHLY REVENUE'!F32) -> 0 | H32: =IF(MOD(H$7,12)=4,MAX(G32*(1+ASSUMPTION!$F$14),ASSUMPTION!$F$11),'MONTHLY REVENUE'!G32) -> 0 | I32: =IF(MOD(I$7,12)=4,MAX(H32*(1+ASSUMPTION!$F$14),ASSUMPTION!$F$11),'MONTHLY REVENUE'!H32) -> 400 | J32: =IF(MOD(J$7,12)=4,MAX(I32*(1+ASSUMPTION!$F$14),ASSUMPTION!$F$11),'MONTHLY REVENUE'!I32) -> 400 | K32: =IF(MOD(K$7,12)=4,MAX(J32*(1+ASSUMPTION!$F$14),ASSUMPTION!$F$11),'MONTHLY REVENUE'!J32) -> 400 | L32: =IF(MOD(L$7,12)=4,MAX(K32*(1+ASSUMPTION!$F$14),ASSUMPTION!$F$11),'MONTHLY REVENUE'!K32) -> 400 | M32: =IF(MOD(M$7,12)=4,MAX(L32*(1+ASSUMPTION!$F$14),ASSUMPTION!$F$11),'MONTHLY REVENUE'!L32) -> 400 | ... AO32: =IF(MOD(AO$7,12)=4,MAX(AN32*(1+ASSUMPTION!$F$14),ASSUMPTION!$F$11),'MONTHLY REVENUE'!AN32) -> 441
A33: Non Alcoholic Beverages | F33: =IF(MOD(F$7,12)=4,MAX(E33*(1+ASSUMPTION!$F$14),ASSUMPTION!$F$12),'MONTHLY REVENUE'!E33) -> 0 | G33: =IF(MOD(G$7,12)=4,MAX(F33*(1+ASSUMPTION!$F$14),ASSUMPTION!$F$12),'MONTHLY REVENUE'!F33) -> 0 | H33: =IF(MOD(H$7,12)=4,MAX(G33*(1+ASSUMPTION!$F$14),ASSUMPTION!$F$12),'MONTHLY REVENUE'!G33) -> 0 | I33: =IF(MOD(I$7,12)=4,MAX(H33*(1+ASSUMPTION!$F$14),ASSUMPTION!$F$12),'MONTHLY REVENUE'!H33) -> 200 | J33: =IF(MOD(J$7,12)=4,MAX(I33*(1+ASSUMPTION!$F$14),ASSUMPTION!$F$12),'MONTHLY REVENUE'!I33) -> 200 | K33: =IF(MOD(K$7,12)=4,MAX(J33*(1+ASSUMPTION!$F$14),ASSUMPTION!$F$12),'MONTHLY REVENUE'!J33) -> 200 | L33: =IF(MOD(L$7,12)=4,MAX(K33*(1+ASSUMPTION!$F$14),ASSUMPTION!$F$12),'MONTHLY REVENUE'!K33) -> 200 | M33: =IF(MOD(M$7,12)=4,MAX(L33*(1+ASSUMPTION!$F$14),ASSUMPTION!$F$12),'MONTHLY REVENUE'!L33) -> 200 | ... AO33: =IF(MOD(AO$7,12)=4,MAX(AN33*(1+ASSUMPTION!$F$14),ASSUMPTION!$F$12),'MONTHLY REVENUE'!AN33) -> 220.5
A34: Food | F34: =IF(MOD(F$7,12)=4,MAX(E34*(1+ASSUMPTION!$F$14),ASSUMPTION!$F$13),'MONTHLY REVENUE'!E34) -> 0 | G34: =IF(MOD(G$7,12)=4,MAX(F34*(1+ASSUMPTION!$F$14),ASSUMPTION!$F$13),'MONTHLY REVENUE'!F34) -> 0 | H34: =IF(MOD(H$7,12)=4,MAX(G34*(1+ASSUMPTION!$F$14),ASSUMPTION!$F$13),'MONTHLY REVENUE'!G34) -> 0 | I34: =IF(MOD(I$7,12)=4,MAX(H34*(1+ASSUMPTION!$F$14),ASSUMPTION!$F$13),'MONTHLY REVENUE'!H34) -> 1000 | J34: =IF(MOD(J$7,12)=4,MAX(I34*(1+ASSUMPTION!$F$14),ASSUMPTION!$F$13),'MONTHLY REVENUE'!I34) -> 1000 | K34: =IF(MOD(K$7,12)=4,MAX(J34*(1+ASSUMPTION!$F$14),ASSUMPTION!$F$13),'MONTHLY REVENUE'!J34) -> 1000 | L34: =IF(MOD(L$7,12)=4,MAX(K34*(1+ASSUMPTION!$F$14),ASSUMPTION!$F$13),'MONTHLY REVENUE'!K34) -> 1000 | M34: =IF(MOD(M$7,12)=4,MAX(L34*(1+ASSUMPTION!$F$14),ASSUMPTION!$F$13),'MONTHLY REVENUE'!L34) -> 1000 | ... AO34: =IF(MOD(AO$7,12)=4,MAX(AN34*(1+ASSUMPTION!$F$14),ASSUMPTION!$F$13),'MONTHLY REVENUE'!AN34) -> 1102.5
A35: TOTAL | F35: =SUM(F32:F34) -> 0 | G35: =SUM(G32:G34) -> 0 | H35: =SUM(H32:H34) -> 0 | I35: =SUM(I32:I34) -> 1600 | J35: =SUM(J32:J34) -> 1600 | K35: =SUM(K32:K34) -> 1600 | L35: =SUM(L32:L34) -> 1600 | M35: =SUM(M32:M34) -> 1600 | ... AO35: =SUM(AO32:AO34) -> 1764
A37: WEEKENDS
A38: LUNCH
A39: Alcoholic Beverages | F39: =IF(MOD(F$7,12)=4,MAX(E39*(1+ASSUMPTION!$C$14),ASSUMPTION!$C$11),'MONTHLY REVENUE'!E39) -> 0 | G39: =IF(MOD(G$7,12)=4,MAX(F39*(1+ASSUMPTION!$C$14),ASSUMPTION!$C$11),'MONTHLY REVENUE'!F39) -> 0 | H39: =IF(MOD(H$7,12)=4,MAX(G39*(1+ASSUMPTION!$C$14),ASSUMPTION!$C$11),'MONTHLY REVENUE'!G39) -> 0 | I39: =IF(MOD(I$7,12)=4,MAX(H39*(1+ASSUMPTION!$C$14),ASSUMPTION!$C$11),'MONTHLY REVENUE'!H39) -> 500 | J39: =IF(MOD(J$7,12)=4,MAX(I39*(1+ASSUMPTION!$C$14),ASSUMPTION!$C$11),'MONTHLY REVENUE'!I39) -> 500 | K39: =IF(MOD(K$7,12)=4,MAX(J39*(1+ASSUMPTION!$C$14),ASSUMPTION!$C$11),'MONTHLY REVENUE'!J39) -> 500 | L39: =IF(MOD(L$7,12)=4,MAX(K39*(1+ASSUMPTION!$C$14),ASSUMPTION!$C$11),'MONTHLY REVENUE'!K39) -> 500 | M39: =IF(MOD(M$7,12)=4,MAX(L39*(1+ASSUMPTION!$C$14),ASSUMPTION!$C$11),'MONTHLY REVENUE'!L39) -> 500 | ... AO39: =IF(MOD(AO$7,12)=4,MAX(AN39*(1+ASSUMPTION!$C$14),ASSUMPTION!$C$11),'MONTHLY REVENUE'!AN39) -> 551.25
A40: Non Alcoholic Beverages | F40: =IF(MOD(F$7,12)=4,MAX(E40*(1+ASSUMPTION!$C$14),ASSUMPTION!$C$12),'MONTHLY REVENUE'!E40) -> 0 | G40: =IF(MOD(G$7,12)=4,MAX(F40*(1+ASSUMPTION!$C$14),ASSUMPTION!$C$12),'MONTHLY REVENUE'!F40) -> 0 | H40: =IF(MOD(H$7,12)=4,MAX(G40*(1+ASSUMPTION!$C$14),ASSUMPTION!$C$12),'MONTHLY REVENUE'!G40) -> 0 | I40: =IF(MOD(I$7,12)=4,MAX(H40*(1+ASSUMPTION!$C$14),ASSUMPTION!$C$12),'MONTHLY REVENUE'!H40) -> 200 | J40: =IF(MOD(J$7,12)=4,MAX(I40*(1+ASSUMPTION!$C$14),ASSUMPTION!$C$12),'MONTHLY REVENUE'!I40) -> 200 | K40: =IF(MOD(K$7,12)=4,MAX(J40*(1+ASSUMPTION!$C$14),ASSUMPTION!$C$12),'MONTHLY REVENUE'!J40) -> 200 | L40: =IF(MOD(L$7,12)=4,MAX(K40*(1+ASSUMPTION!$C$14),ASSUMPTION!$C$12),'MONTHLY REVENUE'!K40) -> 200 | M40: =IF(MOD(M$7,12)=4,MAX(L40*(1+ASSUMPTION!$C$14),ASSUMPTION!$C$12),'MONTHLY REVENUE'!L40) -> 200 | ... AO40: =IF(MOD(AO$7,12)=4,MAX(AN40*(1+ASSUMPTION!$C$14),ASSUMPTION!$C$12),'MONTHLY REVENUE'!AN40) -> 220.5
A41: Food | F41: =IF(MOD(F$7,12)=4,MAX(E41*(1+ASSUMPTION!$C$14),ASSUMPTION!$C$13),'MONTHLY REVENUE'!E41) -> 0 | G41: =IF(MOD(G$7,12)=4,MAX(F41*(1+ASSUMPTION!$C$14),ASSUMPTION!$C$13),'MONTHLY REVENUE'!F41) -> 0 | H41: =IF(MOD(H$7,12)=4,MAX(G41*(1+ASSUMPTION!$C$14),ASSUMPTION!$C$13),'MONTHLY REVENUE'!G41) -> 0 | I41: =IF(MOD(I$7,12)=4,MAX(H41*(1+ASSUMPTION!$C$14),ASSUMPTION!$C$13),'MONTHLY REVENUE'!H41) -> 1000 | J41: =IF(MOD(J$7,12)=4,MAX(I41*(1+ASSUMPTION!$C$14),ASSUMPTION!$C$13),'MONTHLY REVENUE'!I41) -> 1000 | K41: =IF(MOD(K$7,12)=4,MAX(J41*(1+ASSUMPTION!$C$14),ASSUMPTION!$C$13),'MONTHLY REVENUE'!J41) -> 1000 | L41: =IF(MOD(L$7,12)=4,MAX(K41*(1+ASSUMPTION!$C$14),ASSUMPTION!$C$13),'MONTHLY REVENUE'!K41) -> 1000 | M41: =IF(MOD(M$7,12)=4,MAX(L41*(1+ASSUMPTION!$C$14),ASSUMPTION!$C$13),'MONTHLY REVENUE'!L41) -> 1000 | ... AO41: =IF(MOD(AO$7,12)=4,MAX(AN41*(1+ASSUMPTION!$C$14),ASSUMPTION!$C$13),'MONTHLY REVENUE'!AN41) -> 1102.5
A42: TOTAL | F42: =SUM(F39:F41) -> 0 | G42: =SUM(G39:G41) -> 0 | H42: =SUM(H39:H41) -> 0 | I42: =SUM(I39:I41) -> 1700 | J42: =SUM(J39:J41) -> 1700 | K42: =SUM(K39:K41) -> 1700 | L42: =SUM(L39:L41) -> 1700 | M42: =SUM(M39:M41) -> 1700 | ... AO42: =SUM(AO39:AO41) -> 1874.25
A44: DINNER
A45: Alcoholic Beverages | F45: =IF(MOD(F$7,12)=4,MAX(E45*(1+ASSUMPTION!$C$14),ASSUMPTION!$G$11),'MONTHLY REVENUE'!E45) -> 0 | G45: =IF(MOD(G$7,12)=4,MAX(F45*(1+ASSUMPTION!$C$14),ASSUMPTION!$G$11),'MONTHLY REVENUE'!F45) -> 0 | H45: =IF(MOD(H$7,12)=4,MAX(G45*(1+ASSUMPTION!$C$14),ASSUMPTION!$G$11),'MONTHLY REVENUE'!G45) -> 0 | I45: =IF(MOD(I$7,12)=4,MAX(H45*(1+ASSUMPTION!$C$14),ASSUMPTION!$G$11),'MONTHLY REVENUE'!H45) -> 650 | J45: =IF(MOD(J$7,12)=4,MAX(I45*(1+ASSUMPTION!$C$14),ASSUMPTION!$G$11),'MONTHLY REVENUE'!I45) -> 650 | K45: =IF(MOD(K$7,12)=4,MAX(J45*(1+ASSUMPTION!$C$14),ASSUMPTION!$G$11),'MONTHLY REVENUE'!J45) -> 650 | L45: =IF(MOD(L$7,12)=4,MAX(K45*(1+ASSUMPTION!$C$14),ASSUMPTION!$G$11),'MONTHLY REVENUE'!K45) -> 650 | M45: =IF(MOD(M$7,12)=4,MAX(L45*(1+ASSUMPTION!$C$14),ASSUMPTION!$G$11),'MONTHLY REVENUE'!L45) -> 650 | ... AO45: =IF(MOD(AO$7,12)=4,MAX(AN45*(1+ASSUMPTION!$C$14),ASSUMPTION!$G$11),'MONTHLY REVENUE'!AN45) -> 716.625
A46: Non Alcoholic Beverages | F46: =IF(MOD(F$7,12)=4,MAX(E46*(1+ASSUMPTION!$C$14),ASSUMPTION!$G$12),'MONTHLY REVENUE'!E46) -> 0 | G46: =IF(MOD(G$7,12)=4,MAX(F46*(1+ASSUMPTION!$C$14),ASSUMPTION!$G$12),'MONTHLY REVENUE'!F46) -> 0 | H46: =IF(MOD(H$7,12)=4,MAX(G46*(1+ASSUMPTION!$C$14),ASSUMPTION!$G$12),'MONTHLY REVENUE'!G46) -> 0 | I46: =IF(MOD(I$7,12)=4,MAX(H46*(1+ASSUMPTION!$C$14),ASSUMPTION!$G$12),'MONTHLY REVENUE'!H46) -> 250 | J46: =IF(MOD(J$7,12)=4,MAX(I46*(1+ASSUMPTION!$C$14),ASSUMPTION!$G$12),'MONTHLY REVENUE'!I46) -> 250 | K46: =IF(MOD(K$7,12)=4,MAX(J46*(1+ASSUMPTION!$C$14),ASSUMPTION!$G$12),'MONTHLY REVENUE'!J46) -> 250 | L46: =IF(MOD(L$7,12)=4,MAX(K46*(1+ASSUMPTION!$C$14),ASSUMPTION!$G$12),'MONTHLY REVENUE'!K46) -> 250 | M46: =IF(MOD(M$7,12)=4,MAX(L46*(1+ASSUMPTION!$C$14),ASSUMPTION!$G$12),'MONTHLY REVENUE'!L46) -> 250 | ... AO46: =IF(MOD(AO$7,12)=4,MAX(AN46*(1+ASSUMPTION!$C$14),ASSUMPTION!$G$12),'MONTHLY REVENUE'!AN46) -> 275.625
A47: Food | F47: =IF(MOD(F$7,12)=4,MAX(E47*(1+ASSUMPTION!$C$14),ASSUMPTION!$G$13),'MONTHLY REVENUE'!E47) -> 0 | G47: =IF(MOD(G$7,12)=4,MAX(F47*(1+ASSUMPTION!$C$14),ASSUMPTION!$G$13),'MONTHLY REVENUE'!F47) -> 0 | H47: =IF(MOD(H$7,12)=4,MAX(G47*(1+ASSUMPTION!$C$14),ASSUMPTION!$G$13),'MONTHLY REVENUE'!G47) -> 0 | I47: =IF(MOD(I$7,12)=4,MAX(H47*(1+ASSUMPTION!$C$14),ASSUMPTION!$G$13),'MONTHLY REVENUE'!H47) -> 1000 | J47: =IF(MOD(J$7,12)=4,MAX(I47*(1+ASSUMPTION!$C$14),ASSUMPTION!$G$13),'MONTHLY REVENUE'!I47) -> 1000 | K47: =IF(MOD(K$7,12)=4,MAX(J47*(1+ASSUMPTION!$C$14),ASSUMPTION!$G$13),'MONTHLY REVENUE'!J47) -> 1000 | L47: =IF(MOD(L$7,12)=4,MAX(K47*(1+ASSUMPTION!$C$14),ASSUMPTION!$G$13),'MONTHLY REVENUE'!K47) -> 1000 | M47: =IF(MOD(M$7,12)=4,MAX(L47*(1+ASSUMPTION!$C$14),ASSUMPTION!$G$13),'MONTHLY REVENUE'!L47) -> 1000 | ... AO47: =IF(MOD(AO$7,12)=4,MAX(AN47*(1+ASSUMPTION!$C$14),ASSUMPTION!$G$13),'MONTHLY REVENUE'!AN47) -> 1102.5
A48: TOTAL | F48: =SUM(F45:F47) -> 0 | G48: =SUM(G45:G47) -> 0 | H48: =SUM(H45:H47) -> 0 | I48: =SUM(I45:I47) -> 1900 | J48: =SUM(J45:J47) -> 1900 | K48: =SUM(K45:K47) -> 1900 | L48: =SUM(L45:L47) -> 1900 | M48: =SUM(M45:M47) -> 1900 | ... AO48: =SUM(AO45:AO47) -> 2094.75
A50: REVENUE PER MONTH
A51: WEEKDAYS
A52: LUNCH
A53: Alcoholic Beverages | F53: =F26*F$15*F$10/DEN -> 0 | G53: =G26*G$15*G$10/DEN -> 0 | H53: =H26*H$15*H$10/DEN -> 0 | I53: =I26*I$15*I$10/DEN -> 1.38 | J53: =J26*J$15*J$10/DEN -> 1.2852 | K53: =K26*K$15*K$10/DEN -> 1.373328 | L53: =L26*L$15*L$10/DEN -> 1.4007946 | M53: =M26*M$15*M$10/DEN -> 1.3638645 | ... AO53: =AO26*AO$15*AO$10/DEN -> 2.8672343
A54: Non Alcoholic Beverages | F54: =F27*F$15*F$10/DEN -> 0 | G54: =G27*G$15*G$10/DEN -> 0 | H54: =H27*H$15*H$10/DEN -> 0 | I54: =I27*I$15*I$10/DEN -> 0.92 | J54: =J27*J$15*J$10/DEN -> 0.8568 | K54: =K27*K$15*K$10/DEN -> 0.915552 | L54: =L27*L$15*L$10/DEN -> 0.93386304 | M54: =M27*M$15*M$10/DEN -> 0.90924301 | ... AO54: =AO27*AO$15*AO$10/DEN -> 1.9114895
A55: Food | F55: =F28*F$15*F$10/DEN -> 0 | G55: =G28*G$15*G$10/DEN -> 0 | H55: =H28*H$15*H$10/DEN -> 0 | I55: =I28*I$15*I$10/DEN -> 4.6 | J55: =J28*J$15*J$10/DEN -> 4.284 | K55: =K28*K$15*K$10/DEN -> 4.57776 | L55: =L28*L$15*L$10/DEN -> 4.6693152 | M55: =M28*M$15*M$10/DEN -> 4.5462151 | ... AO55: =AO28*AO$15*AO$10/DEN -> 9.5574476
A56: TOTAL | F56: =SUM(F53:F55) -> 0 | G56: =SUM(G53:G55) -> 0 | H56: =SUM(H53:H55) -> 0 | I56: =SUM(I53:I55) -> 6.9 | J56: =SUM(J53:J55) -> 6.426 | K56: =SUM(K53:K55) -> 6.86664 | L56: =SUM(L53:L55) -> 7.0039728 | M56: =SUM(M53:M55) -> 6.8193226 | ... AO56: =SUM(AO53:AO55) -> 14.336171
A58: DINNER
A59: Alcoholic Beverages | F59: =F32*F$16*F$10/DEN -> 0 | G59: =G32*G$16*G$10/DEN -> 0 | H59: =H32*H$16*H$10/DEN -> 0 | I59: =I32*I$16*I$10/DEN -> 2.392 | J59: =J32*J$16*J$10/DEN -> 2.22768 | K59: =K32*K$16*K$10/DEN -> 2.3804352 | L59: =L32*L$16*L$10/DEN -> 2.4280439 | M59: =M32*M$16*M$10/DEN -> 2.3640318 | ... AO59: =AO32*AO$16*AO$10/DEN -> 4.9698728
A60: Non Alcoholic Beverages | F60: =F33*F$16*F$10/DEN -> 0 | G60: =G33*G$16*G$10/DEN -> 0 | H60: =H33*H$16*H$10/DEN -> 0 | I60: =I33*I$16*I$10/DEN -> 1.196 | J60: =J33*J$16*J$10/DEN -> 1.11384 | K60: =K33*K$16*K$10/DEN -> 1.1902176 | L60: =L33*L$16*L$10/DEN -> 1.214022 | M60: =M33*M$16*M$10/DEN -> 1.1820159 | ... AO60: =AO33*AO$16*AO$10/DEN -> 2.4849364
A61: Food | F61: =F34*F$16*F$10/DEN -> 0 | G61: =G34*G$16*G$10/DEN -> 0 | H61: =H34*H$16*H$10/DEN -> 0 | I61: =I34*I$16*I$10/DEN -> 5.98 | J61: =J34*J$16*J$10/DEN -> 5.5692 | K61: =K34*K$16*K$10/DEN -> 5.951088 | L61: =L34*L$16*L$10/DEN -> 6.0701098 | M61: =M34*M$16*M$10/DEN -> 5.9100796 | ... AO61: =AO34*AO$16*AO$10/DEN -> 12.424682
A62: TOTAL | F62: =SUM(F59:F61) -> 0 | G62: =SUM(G59:G61) -> 0 | H62: =SUM(H59:H61) -> 0 | I62: =SUM(I59:I61) -> 9.568 | J62: =SUM(J59:J61) -> 8.91072 | K62: =SUM(K59:K61) -> 9.5217408 | L62: =SUM(L59:L61) -> 9.7121756 | M62: =SUM(M59:M61) -> 9.4561273 | ... AO62: =SUM(AO59:AO61) -> 19.879491
A64: WEEKENDS
A65: LUNCH
A66: Alcoholic Beverages | F66: =F39*F$20*F$11/DEN -> 0 | G66: =G39*G$20*G$11/DEN -> 0 | H66: =H39*H$20*H$11/DEN -> 0 | I66: =I39*I$20*I$11/DEN -> 1.04 | J66: =J39*J$20*J$11/DEN -> 1.352 | K66: =K39*K$20*K$11/DEN -> 1.124864 | L66: =L39*L$20*L$11/DEN -> 1.3160909 | M66: =M39*M$20*M$11/DEN -> 1.3687345 | ... AO66: =AO39*AO$20*AO$11/DEN -> 3.528
A67: Non Alcoholic Beverages | F67: =F40*F$20*F$11/DEN -> 0 | G67: =G40*G$20*G$11/DEN -> 0 | H67: =H40*H$20*H$11/DEN -> 0 | I67: =I40*I$20*I$11/DEN -> 0.416 | J67: =J40*J$20*J$11/DEN -> 0.5408 | K67: =K40*K$20*K$11/DEN -> 0.4499456 | L67: =L40*L$20*L$11/DEN -> 0.52643635 | M67: =M40*M$20*M$11/DEN -> 0.54749381 | ... AO67: =AO40*AO$20*AO$11/DEN -> 1.4112
A68: Food | F68: =F41*F$20*F$11/DEN -> 0 | G68: =G41*G$20*G$11/DEN -> 0 | H68: =H41*H$20*H$11/DEN -> 0 | I68: =I41*I$20*I$11/DEN -> 2.08 | J68: =J41*J$20*J$11/DEN -> 2.704 | K68: =K41*K$20*K$11/DEN -> 2.249728 | L68: =L41*L$20*L$11/DEN -> 2.6321818 | M68: =M41*M$20*M$11/DEN -> 2.737469 | ... AO68: =AO41*AO$20*AO$11/DEN -> 7.056
A69: TOTAL | F69: =SUM(F66:F68) -> 0 | G69: =SUM(G66:G68) -> 0 | H69: =SUM(H66:H68) -> 0 | I69: =SUM(I66:I68) -> 3.536 | J69: =SUM(J66:J68) -> 4.5968 | K69: =SUM(K66:K68) -> 3.8245376 | L69: =SUM(L66:L68) -> 4.474709 | M69: =SUM(M66:M68) -> 4.6536974 | ... AO69: =SUM(AO66:AO68) -> 11.9952
A71: DINNER
A72: Alcoholic Beverages | F72: =F45*F$21*F$11/DEN -> 0 | G72: =G45*G$21*G$11/DEN -> 0 | H72: =H45*H$21*H$11/DEN -> 0 | I72: =I45*I$21*I$11/DEN -> 1.56 | J72: =J45*J$21*J$11/DEN -> 2.028 | K72: =K45*K$21*K$11/DEN -> 1.687296 | L72: =L45*L$21*L$11/DEN -> 1.9741363 | M72: =M45*M$21*M$11/DEN -> 2.0531018 | ... AO72: =AO45*AO$21*AO$11/DEN -> 5.1597
A73: Non Alcoholic Beverages | F73: =F46*F$21*F$11/DEN -> 0 | G73: =G46*G$21*G$11/DEN -> 0 | H73: =H46*H$21*H$11/DEN -> 0 | I73: =I46*I$21*I$11/DEN -> 0.6 | J73: =J46*J$21*J$11/DEN -> 0.78 | K73: =K46*K$21*K$11/DEN -> 0.64896 | L73: =L46*L$21*L$11/DEN -> 0.7592832 | M73: =M46*M$21*M$11/DEN -> 0.78965453 | ... AO73: =AO46*AO$21*AO$11/DEN -> 1.9845
A74: Food | F74: =F47*F$21*F$11/DEN -> 0 | G74: =G47*G$21*G$11/DEN -> 0 | H74: =H47*H$21*H$11/DEN -> 0 | I74: =I47*I$21*I$11/DEN -> 2.4 | J74: =J47*J$21*J$11/DEN -> 3.12 | K74: =K47*K$21*K$11/DEN -> 2.59584 | L74: =L47*L$21*L$11/DEN -> 3.0371328 | M74: =M47*M$21*M$11/DEN -> 3.1586181 | ... AO74: =AO47*AO$21*AO$11/DEN -> 7.938
A75: TOTAL | F75: =SUM(F72:F74) -> 0 | G75: =SUM(G72:G74) -> 0 | H75: =SUM(H72:H74) -> 0 | I75: =SUM(I72:I74) -> 4.56 | J75: =SUM(J72:J74) -> 5.928 | K75: =SUM(K72:K74) -> 4.932096 | L75: =SUM(L72:L74) -> 5.7705523 | M75: =SUM(M72:M74) -> 6.0013744 | ... AO75: =SUM(AO72:AO74) -> 15.0822
A77: TOTAL REVENUE FOR MONTH
A78: Alcoholic Beverages | F78: =F53+F59+F66+F72 -> 0 | G78: =G53+G59+G66+G72 -> 0 | H78: =H53+H59+H66+H72 -> 0 | I78: =I53+I59+I66+I72 -> 6.372 | J78: =J53+J59+J66+J72 -> 6.89288 | K78: =K53+K59+K66+K72 -> 6.5659232 | L78: =L53+L59+L66+L72 -> 7.1190657 | M78: =M53+M59+M66+M72 -> 7.1497326 | ... AO78: =AO53+AO59+AO66+AO72 -> 16.524807
A79: Non Alcoholic Beverages | F79: =F54+F60+F67+F73 -> 0 | G79: =G54+G60+G67+G73 -> 0 | H79: =H54+H60+H67+H73 -> 0 | I79: =I54+I60+I67+I73 -> 3.132 | J79: =J54+J60+J67+J73 -> 3.29144 | K79: =K54+K60+K67+K73 -> 3.2046752 | L79: =L54+L60+L67+L73 -> 3.4336045 | M79: =M54+M60+M67+M73 -> 3.4284073 | ... AO79: =AO54+AO60+AO67+AO73 -> 7.7921259
A80: Food | F80: =F55+F61+F68+F74 -> 0 | G80: =G55+G61+G68+G74 -> 0 | H80: =H55+H61+H68+H74 -> 0 | I80: =I55+I61+I68+I74 -> 15.06 | J80: =J55+J61+J68+J74 -> 15.6772 | K80: =K55+K61+K68+K74 -> 15.374416 | L80: =L55+L61+L68+L74 -> 16.40874 | M80: =M55+M61+M68+M74 -> 16.352382 | ... AO80: =AO55+AO61+AO68+AO74 -> 36.97613
A81: TOTAL | F81: =SUM(F78:F80) -> 0 | G81: =SUM(G78:G80) -> 0 | H81: =SUM(H78:H80) -> 0 | I81: =SUM(I78:I80) -> 24.564 | J81: =SUM(J78:J80) -> 25.86152 | K81: =SUM(K78:K80) -> 25.145014 | L81: =SUM(L78:L80) -> 26.96141 | M81: =SUM(M78:M80) -> 26.930522 | ... AO81: =SUM(AO78:AO80) -> 61.293062
A84: END OF SHEET

Sheet MONTHLY P&L
A1: ALL FINAL VALUES IN | B1: =CONVERTER!C1 -> LAKHS
E7: 0 | F7: 1 | G7: 2 | H7: 3 | I7: 4 | J7: 5 | K7: 6 | L7: 7 | M7: 8 | N7: 9 | O7: 10 | P7: 11 | Q7: 12 | R7: 13 | S7: 14 | T7: 15 | U7: 16 | V7: 17 | W7: 18 | X7: 19 | Y7: 20 | Z7: 21 | AA7: 22 | AB7: 23 | AC7: 24 | AD7: 25 | AE7: 26 | AF7: 27 | AG7: 28 | AH7: 29 | AI7: 30 | AJ7: 31 | AK7: 32 | AL7: 33 | AM7: 34 | AN7: 35 | AO7: 36
F8: =EOMONTH(ASSUMPTION!G3,0) -> 43951 | G8: =EOMONTH(F8,1) -> 43982 | H8: =EOMONTH(G8,1) -> 44012 | I8: =EOMONTH(H8,1) -> 44043 | J8: =EOMONTH(I8,1) -> 44074 | K8: =EOMONTH(J8,1) -> 44104 | L8: =EOMONTH(K8,1) -> 44135 | M8: =EOMONTH(L8,1) -> 44165 | N8: =EOMONTH(M8,1) -> 44196 | ... AO8: =EOMONTH(AN8,1) -> 45016
A9: REVENUE
A10: Alcoholic Beverages | F10: ='MONTHLY REVENUE'!F78 -> 0 | G10: ='MONTHLY REVENUE'!G78 -> 0 | H10: ='MONTHLY REVENUE'!H78 -> 0 | I10: ='MONTHLY REVENUE'!I78 -> 6.372 | J10: ='MONTHLY REVENUE'!J78 -> 6.89288 | K10: ='MONTHLY REVENUE'!K78 -> 6.5659232 | L10: ='MONTHLY REVENUE'!L78 -> 7.1190657 | M10: ='MONTHLY REVENUE'!M78 -> 7.1497326 | ... AO10: ='MONTHLY REVENUE'!AO78 -> 16.524807
A11: Non Alcoholic Beverages | F11: ='MONTHLY REVENUE'!F79 -> 0 | G11: ='MONTHLY REVENUE'!G79 -> 0 | H11: ='MONTHLY REVENUE'!H79 -> 0 | I11: ='MONTHLY REVENUE'!I79 -> 3.132 | J11: ='MONTHLY REVENUE'!J79 -> 3.29144 | K11: ='MONTHLY REVENUE'!K79 -> 3.2046752 | L11: ='MONTHLY REVENUE'!L79 -> 3.4336045 | M11: ='MONTHLY REVENUE'!M79 -> 3.4284073 | ... AO11: ='MONTHLY REVENUE'!AO79 -> 7.7921259
A12: FOOD | F12: ='MONTHLY REVENUE'!F80 -> 0 | G12: ='MONTHLY REVENUE'!G80 -> 0 | H12: ='MONTHLY REVENUE'!H80 -> 0 | I12: ='MONTHLY REVENUE'!I80 -> 15.06 | J12: ='MONTHLY REVENUE'!J80 -> 15.6772 | K12: ='MONTHLY REVENUE'!K80 -> 15.374416 | L12: ='MONTHLY REVENUE'!L80 -> 16.40874 | M12: ='MONTHLY REVENUE'!M80 -> 16.352382 | ... AO12: ='MONTHLY REVENUE'!AO80 -> 36.97613
A13: TOTAL | F13: ='MONTHLY REVENUE'!F81 -> 0 | G13: ='MONTHLY REVENUE'!G81 -> 0 | H13: ='MONTHLY REVENUE'!H81 -> 0 | I13: ='MONTHLY REVENUE'!I81 -> 24.564 | J13: ='MONTHLY REVENUE'!J81 -> 25.86152 | K13: ='MONTHLY REVENUE'!K81 -> 25.145014 | L13: ='MONTHLY REVENUE'!L81 -> 26.96141 | M13: ='MONTHLY REVENUE'!M81 -> 26.930522 | ... AO13: ='MONTHLY REVENUE'!AO81 -> 61.293062
A15: LESS:DIRECT EXPENSES
A16: =ASSUMPTION!A25 -> Alcoholic Beverage cost (% of revenue) | F16: =F10*ASSUMPTION!$G25/DEN -> 0 | G16: =G10*ASSUMPTION!$G25/DEN -> 0 | H16: =H10*ASSUMPTION!$G25/DEN -> 0 | I16: =I10*ASSUMPTION!$G25 -> 2.2302 | J16: =J10*ASSUMPTION!$G25 -> 2.412508 | K16: =K10*ASSUMPTION!$G25 -> 2.2980731 | L16: =L10*ASSUMPTION!$G25 -> 2.491673 | M16: =M10*ASSUMPTION!$G25 -> 2.5024064 | N16: =N10*ASSUMPTION!$G25 -> 2.5647616 | O16: =O10*ASSUMPTION!$G25 -> 2.7967766 | P16: =P10*ASSUMPTION!$G25 -> 2.5161891 | ... AO16: =AO10*ASSUMPTION!$G25 -> 5.7836825
A17: =ASSUMPTION!A26 -> Non Alcoholic Beverages (% of revenue) | F17: =F11*ASSUMPTION!$G26/DEN -> 0 | G17: =G11*ASSUMPTION!$G26/DEN -> 0 | H17: =H11*ASSUMPTION!$G26/DEN -> 0 | I17: =I11*ASSUMPTION!$G26 -> 1.2528 | J17: =J11*ASSUMPTION!$G26 -> 1.316576 | K17: =K11*ASSUMPTION!$G26 -> 1.2818701 | L17: =L11*ASSUMPTION!$G26 -> 1.3734418 | M17: =M11*ASSUMPTION!$G26 -> 1.3713629 | N17: =N11*ASSUMPTION!$G26 -> 1.4289417 | O17: =O11*ASSUMPTION!$G26 -> 1.5130804 | P17: =P11*ASSUMPTION!$G26 -> 1.3802273 | ... AO17: =AO11*ASSUMPTION!$G26 -> 3.1168504
A18: =ASSUMPTION!A27 -> Food (% of revenue) | F18: =F12*ASSUMPTION!$G27/DEN -> 0 | G18: =G12*ASSUMPTION!$G27/DEN -> 0 | H18: =H12*ASSUMPTION!$G27/DEN -> 0 | I18: =I12*ASSUMPTION!$G27 -> 4.518 | J18: =J12*ASSUMPTION!$G27 -> 4.70316 | K18: =K12*ASSUMPTION!$G27 -> 4.6123248 | L18: =L12*ASSUMPTION!$G27 -> 4.9226219 | M18: =M12*ASSUMPTION!$G27 -> 4.9057145 | N18: =N12*ASSUMPTION!$G27 -> 5.139534 | O18: =O12*ASSUMPTION!$G27 -> 5.3893546 | P18: =P12*ASSUMPTION!$G27 -> 4.9389848 | ... AO18: =AO12*ASSUMPTION!$G27 -> 11.092839
A19: Staff Salary | F19: =IF(MOD(F7,12)=4,MAX(ASSUMPTION!$G$40/DEN,'MONTHLY P&L'!E19*(1+ASSUMPTION!$G$41)),'MONTHLY P&L'!E19) -> 0 | G19: =IF(MOD(G7,12)=4,MAX(ASSUMPTION!$G$40/DEN,'MONTHLY P&L'!F19*(1+ASSUMPTION!$G$41)),'MONTHLY P&L'!F19) -> 0 | H19: =IF(MOD(H7,12)=4,MAX(ASSUMPTION!$G$40/DEN,'MONTHLY P&L'!G19*(1+ASSUMPTION!$G$41)),'MONTHLY P&L'!G19) -> 0 | I19: =IF(MOD(I7,12)=4,MAX(ASSUMPTION!$G$40/DEN,'MONTHLY P&L'!H19*(1+ASSUMPTION!$G$41)),'MONTHLY P&L'!H19) -> 9.86 | J19: =IF(MOD(J7,12)=4,MAX(ASSUMPTION!$G$40/DEN,'MONTHLY P&L'!I19*(1+ASSUMPTION!$G$41)),'MONTHLY P&L'!I19) -> 9.86 | K19: =IF(MOD(K7,12)=4,MAX(ASSUMPTION!$G$40/DEN,'MONTHLY P&L'!J19*(1+ASSUMPTION!$G$41)),'MONTHLY P&L'!J19) -> 9.86 | L19: =IF(MOD(L7,12)=4,MAX(ASSUMPTION!$G$40/DEN,'MONTHLY P&L'!K19*(1+ASSUMPTION!$G$41)),'MONTHLY P&L'!K19) -> 9.86 | M19: =IF(MOD(M7,12)=4,MAX(ASSUMPTION!$G$40/DEN,'MONTHLY P&L'!L19*(1+ASSUMPTION!$G$41)),'MONTHLY P&L'!L19) -> 9.86 | ... AO19: =IF(MOD(AO7,12)=4,MAX(ASSUMPTION!$G$40/DEN,'MONTHLY P&L'!AN19*(1+ASSUMPTION!$G$41)),'MONTHLY P&L'!AN19) -> 11.500704
A20: Total Direct Expenses | F20: =SUM(F16:F19) -> 0 | G20: =SUM(G16:G19) -> 0 | H20: =SUM(H16:H19) -> 0 | I20: =SUM(I16:I19) -> 17.861 | J20: =SUM(J16:J19) -> 18.292244 | K20: =SUM(K16:K19) -> 18.052268 | L20: =SUM(L16:L19) -> 18.647737 | M20: =SUM(M16:M19) -> 18.639484 | ... AO20: =SUM(AO16:AO19) -> 31.494076
A22: LESS:INDIRECT EXPENSES
A23: OTHER STAFF SALARY | F23: =IF(MOD(F7,12)=4,MAX(ASSUMPTION!$G$50/DEN,'MONTHLY P&L'!E23*(1+ASSUMPTION!$G$41)),'MONTHLY P&L'!E23) -> 0 | G23: =IF(MOD(G7,12)=4,MAX(ASSUMPTION!$G$50/DEN,'MONTHLY P&L'!F23*(1+ASSUMPTION!$G$41)),'MONTHLY P&L'!F23) -> 0 | H23: =IF(MOD(H7,12)=4,MAX(ASSUMPTION!$G$50/DEN,'MONTHLY P&L'!G23*(1+ASSUMPTION!$G$41)),'MONTHLY P&L'!G23) -> 0 | I23: =IF(MOD(I7,12)=4,MAX(ASSUMPTION!$G$50/DEN,'MONTHLY P&L'!H23*(1+ASSUMPTION!$G$41)),'MONTHLY P&L'!H23) -> 3.8 | J23: =IF(MOD(J7,12)=4,MAX(ASSUMPTION!$G$50/DEN,'MONTHLY P&L'!I23*(1+ASSUMPTION!$G$41)),'MONTHLY P&L'!I23) -> 3.8 | K23: =IF(MOD(K7,12)=4,MAX(ASSUMPTION!$G$50/DEN,'MONTHLY P&L'!J23*(1+ASSUMPTION!$G$41)),'MONTHLY P&L'!J23) -> 3.8 | L23: =IF(MOD(L7,12)=4,MAX(ASSUMPTION!$G$50/DEN,'MONTHLY P&L'!K23*(1+ASSUMPTION!$G$41)),'MONTHLY P&L'!K23) -> 3.8 | M23: =IF(MOD(M7,12)=4,MAX(ASSUMPTION!$G$50/DEN,'MONTHLY P&L'!L23*(1+ASSUMPTION!$G$41)),'MONTHLY P&L'!L23) -> 3.8 | ... AO23: =IF(MOD(AO7,12)=4,MAX(ASSUMPTION!$G$50/DEN,'MONTHLY P&L'!AN23*(1+ASSUMPTION!$G$41)),'MONTHLY P&L'!AN23) -> 4.43232
A24: =ASSUMPTION!A52 -> Rotalty to brand (% Of Revenue) | F24: =F13*ASSUMPTION!$G$52/DEN -> 0 | G24: =G13*ASSUMPTION!$G$52/DEN -> 0 | H24: =H13*ASSUMPTION!$G$52/DEN -> 0 | I24: =I13*ASSUMPTION!$G$52 -> 1.2282 | J24: =J13*ASSUMPTION!$G$52 -> 1.293076 | K24: =K13*ASSUMPTION!$G$52 -> 1.2572507 | L24: =L13*ASSUMPTION!$G$52 -> 1.3480705 | M24: =M13*ASSUMPTION!$G$52 -> 1.3465261 | N24: =N13*ASSUMPTION!$G$52 -> 1.4016012 | O24: =O13*ASSUMPTION!$G$52 -> 1.4869003 | P24: =P13*ASSUMPTION!$G$52 -> 1.3551481 | ... AO24: =AO13*ASSUMPTION!$G$52 -> 3.0646531
A25: =ASSUMPTION!A53 -> Rent (as per contract) (% of revenue) | F25: ='MONTHLY P&L'!F13*ASSUMPTION!$G$53 -> 0 | G25: ='MONTHLY P&L'!G13*ASSUMPTION!$G$53 -> 0 | H25: ='MONTHLY P&L'!H13*ASSUMPTION!$G$53 -> 0 | I25: ='MONTHLY P&L'!I13*ASSUMPTION!$G$53 -> 2.4564 | J25: ='MONTHLY P&L'!J13*ASSUMPTION!$G$53 -> 2.586152 | K25: ='MONTHLY P&L'!K13*ASSUMPTION!$G$53 -> 2.5145014 | L25: ='MONTHLY P&L'!L13*ASSUMPTION!$G$53 -> 2.696141 | M25: ='MONTHLY P&L'!M13*ASSUMPTION!$G$53 -> 2.6930522 | ... AO25: ='MONTHLY P&L'!AO13*ASSUMPTION!$G$53 -> 6.1293062
A26: =ASSUMPTION!A54 -> Water Cost (per month) | F26: =IF(MOD(F7,12)=4,MAX(ASSUMPTION!$G$54/DEN,'MONTHLY P&L'!E26*(1+ASSUMPTION!$G$62)),'MONTHLY P&L'!E26) -> 0 | G26: =IF(MOD(G7,12)=4,MAX(ASSUMPTION!$G$54/DEN,'MONTHLY P&L'!F26*(1+ASSUMPTION!$G$62)),'MONTHLY P&L'!F26) -> 0 | H26: =IF(MOD(H7,12)=4,MAX(ASSUMPTION!$G$54/DEN,'MONTHLY P&L'!G26*(1+ASSUMPTION!$G$62)),'MONTHLY P&L'!G26) -> 0 | I26: =IF(MOD(I7,12)=4,MAX(ASSUMPTION!$G$54/DEN,'MONTHLY P&L'!H26*(1+ASSUMPTION!$G$62)),'MONTHLY P&L'!H26) -> 0.1 | J26: =IF(MOD(J7,12)=4,MAX(ASSUMPTION!$G$54/DEN,'MONTHLY P&L'!I26*(1+ASSUMPTION!$G$62)),'MONTHLY P&L'!I26) -> 0.1 | K26: =IF(MOD(K7,12)=4,MAX(ASSUMPTION!$G$54/DEN,'MONTHLY P&L'!J26*(1+ASSUMPTION!$G$62)),'MONTHLY P&L'!J26) -> 0.1 | L26: =IF(MOD(L7,12)=4,MAX(ASSUMPTION!$G$54/DEN,'MONTHLY P&L'!K26*(1+ASSUMPTION!$G$62)),'MONTHLY P&L'!K26) -> 0.1 | M26: =IF(MOD(M7,12)=4,MAX(ASSUMPTION!$G$54/DEN,'MONTHLY P&L'!L26*(1+ASSUMPTION!$G$62)),'MONTHLY P&L'!L26) -> 0.1 | ... AO26: =IF(MOD(AO7,12)=4,MAX(ASSUMPTION!$G$54/DEN,'MONTHLY P&L'!AN26*(1+ASSUMPTION!$G$62)),'MONTHLY P&L'!AN26) -> 0.11664
A27: =ASSUMPTION!A55 -> Maintenance (per month) | F27: =IF(MOD(F7,12)=4,MAX(ASSUMPTION!$G$55,'MONTHLY P&L'!E27*(1+ASSUMPTION!$G$62)),'MONTHLY P&L'!E27) -> 0 | G27: =IF(MOD(G7,12)=4,MAX(ASSUMPTION!$G$55,'MONTHLY P&L'!F27*(1+ASSUMPTION!$G$62)),'MONTHLY P&L'!F27) -> 0 | H27: =IF(MOD(H7,12)=4,MAX(ASSUMPTION!$G$55,'MONTHLY P&L'!G27*(1+ASSUMPTION!$G$62)),'MONTHLY P&L'!G27) -> 0 | I27: =IF(MOD(I7,12)=4,MAX(ASSUMPTION!$G$55/DEN,'MONTHLY P&L'!H27*(1+ASSUMPTION!$G$62)),'MONTHLY P&L'!H27) -> 0.5 | J27: =IF(MOD(J7,12)=4,MAX(ASSUMPTION!$G$55,'MONTHLY P&L'!I27*(1+ASSUMPTION!$G$62)),'MONTHLY P&L'!I27) -> 0.5 | K27: =IF(MOD(K7,12)=4,MAX(ASSUMPTION!$G$55,'MONTHLY P&L'!J27*(1+ASSUMPTION!$G$62)),'MONTHLY P&L'!J27) -> 0.5 | L27: =IF(MOD(L7,12)=4,MAX(ASSUMPTION!$G$55,'MONTHLY P&L'!K27*(1+ASSUMPTION!$G$62)),'MONTHLY P&L'!K27) -> 0.5 | M27: =IF(MOD(M7,12)=4,MAX(ASSUMPTION!$G$55,'MONTHLY P&L'!L27*(1+ASSUMPTION!$G$62)),'MONTHLY P&L'!L27) -> 0.5 | N27: =IF(MOD(N7,12)=4,MAX(ASSUMPTION!$G$55,'MONTHLY P&L'!M27*(1+ASSUMPTION!$G$62)),'MONTHLY P&L'!M27) -> 0.5 | O27: =IF(MOD(O7,12)=4,MAX(ASSUMPTION!$G$55,'MONTHLY P&L'!N27*(1+ASSUMPTION!$G$62)),'MONTHLY P&L'!N27) -> 0.5 | P27: =IF(MOD(P7,12)=4,MAX(ASSUMPTION!$G$55,'MONTHLY P&L'!O27*(1+ASSUMPTION!$G$62)),'MONTHLY P&L'!O27) -> 0.5 | Q27: =IF(MOD(Q7,12)=4,MAX(ASSUMPTION!$G$55,'MONTHLY P&L'!P27*(1+ASSUMPTION!$G$62)),'MONTHLY P&L'!P27) -> 0.5 | ... T27: =IF(MOD(T7,12)=4,MAX(ASSUMPTION!$G$55,'MONTHLY P&L'!S27*(1+ASSUMPTION!$G$62)),'MONTHLY P&L'!S27) -> 0.5 | U27: =IF(MOD(U7,12)=4,MAX(ASSUMPTION!$G$55/DEN,'MONTHLY P&L'!T27*(1+ASSUMPTION!$G$62)),'MONTHLY P&L'!T27) -> 0.54 | V27: =IF(MOD(V7,12)=4,MAX(ASSUMPTION!$G$55,'MONTHLY P&L'!U27*(1+ASSUMPTION!$G$62)),'MONTHLY P&L'!U27) -> 0.54 | W27: =IF(MOD(W7,12)=4,MAX(ASSUMPTION!$G$55,'MONTHLY P&L'!V27*(1+ASSUMPTION!$G$62)),'MONTHLY P&L'!V27) -> 0.54 | X27: =IF(MOD(X7,12)=4,MAX(ASSUMPTION!$G$55,'MONTHLY P&L'!W27*(1+ASSUMPTION!$G$62)),'MONTHLY P&L'!W27) -> 0.54 | Y27: =IF(MOD(Y7,12)=4,MAX(ASSUMPTION!$G$55,'MONTHLY P&L'!X27*(1+ASSUMPTION!$G$62)),'MONTHLY P&L'!X27) -> 0.54 | Z27: =IF(MOD(Z7,12)=4,MAX(ASSUMPTION!$G$55,'MONTHLY P&L'!Y27*(1+ASSUMPTION!$G$62)),'MONTHLY P&L'!Y27) -> 0.54 | AA27: =IF(MOD(AA7,12)=4,MAX(ASSUMPTION!$G$55,'MONTHLY P&L'!Z27*(1+ASSUMPTION!$G$62)),'MONTHLY P&L'!Z27) -> 0.54 | AB27: =IF(MOD(AB7,12)=4,MAX(ASSUMPTION!$G$55,'MONTHLY P&L'!AA27*(1+ASSUMPTION!$G$62)),'MONTHLY P&L'!AA27) -> 0.54 | AC27: =IF(MOD(AC7,12)=4,MAX(ASSUMPTION!$G$55,'MONTHLY P&L'!AB27*(1+ASSUMPTION!$G$62)),'MONTHLY P&L'!AB27) -> 0.54 | ... AF27: =IF(MOD(AF7,12)=4,MAX(ASSUMPTION!$G$55,'MONTHLY P&L'!AE27*(1+ASSUMPTION!$G$62)),'MONTHLY P&L'!AE27) -> 0.54 | AG27: =IF(MOD(AG7,12)=4,MAX(ASSUMPTION!$G$55/DEN,'MONTHLY P&L'!AF27*(1+ASSUMPTION!$G$62)),'MONTHLY P&L'!AF27) -> 0.5832 | AH27: =IF(MOD(AH7,12)=4,MAX(ASSUMPTION!$G$55,'MONTHLY P&L'!AG27*(1+ASSUMPTION!$G$62)),'MONTHLY P&L'!AG27) -> 0.5832 | AI27: =IF(MOD(AI7,12)=4,MAX(ASSUMPTION!$G$55,'MONTHLY P&L'!AH27*(1+ASSUMPTION!$G$62)),'MONTHLY P&L'!AH27) -> 0.5832 | AJ27: =IF(MOD(AJ7,12)=4,MAX(ASSUMPTION!$G$55,'MONTHLY P&L'!AI27*(1+ASSUMPTION!$G$62)),'MONTHLY P&L'!AI27) -> 0.5832 | AK27: =IF(MOD(AK7,12)=4,MAX(ASSUMPTION!$G$55,'MONTHLY P&L'!AJ27*(1+ASSUMPTION!$G$62)),'MONTHLY P&L'!AJ27) -> 0.5832 | AL27: =IF(MOD(AL7,12)=4,MAX(ASSUMPTION!$G$55,'MONTHLY P&L'!AK27*(1+ASSUMPTION!$G$62)),'MONTHLY P&L'!AK27) -> 0.5832 | AM27: =IF(MOD(AM7,12)=4,MAX(ASSUMPTION!$G$55,'MONTHLY P&L'!AL27*(1+ASSUMPTION!$G$62)),'MONTHLY P&L'!AL27) -> 0.5832 | AN27: =IF(MOD(AN7,12)=4,MAX(ASSUMPTION!$G$55,'MONTHLY P&L'!AM27*(1+ASSUMPTION!$G$62)),'MONTHLY P&L'!AM27) -> 0.5832 | AO27: =IF(MOD(AO7,12)=4,MAX(ASSUMPTION!$G$55/DEN,'MONTHLY P&L'!AN27*(1+ASSUMPTION!$G$62)),'MONTHLY P&L'!AN27) -> 0.5832
A28: =ASSUMPTION!A56 -> Marketing cost (per month) | F28: =IF(MOD(F7,12)=4,MAX(ASSUMPTION!$G$56/DEN,'MONTHLY P&L'!E28*(1+ASSUMPTION!$G$62)),'MONTHLY P&L'!E28) -> 0 | G28: =IF(MOD(G7,12)=4,MAX(ASSUMPTION!$G$56/DEN,'MONTHLY P&L'!F28*(1+ASSUMPTION!$G$62)),'MONTHLY P&L'!F28) -> 0 | H28: =IF(MOD(H7,12)=4,MAX(ASSUMPTION!$G$56/DEN,'MONTHLY P&L'!G28*(1+ASSUMPTION!$G$62)),'MONTHLY P&L'!G28) -> 0 | I28: =IF(MOD(I7,12)=4,MAX(ASSUMPTION!$G$56/DEN,'MONTHLY P&L'!H28*(1+ASSUMPTION!$G$62)),'MONTHLY P&L'!H28) -> 0.25 | J28: =IF(MOD(J7,12)=4,MAX(ASSUMPTION!$G$56/DEN,'MONTHLY P&L'!I28*(1+ASSUMPTION!$G$62)),'MONTHLY P&L'!I28) -> 0.25 | K28: =IF(MOD(K7,12)=4,MAX(ASSUMPTION!$G$56/DEN,'MONTHLY P&L'!J28*(1+ASSUMPTION!$G$62)),'MONTHLY P&L'!J28) -> 0.25 | L28: =IF(MOD(L7,12)=4,MAX(ASSUMPTION!$G$56/DEN,'MONTHLY P&L'!K28*(1+ASSUMPTION!$G$62)),'MONTHLY P&L'!K28) -> 0.25 | M28: =IF(MOD(M7,12)=4,MAX(ASSUMPTION!$G$56/DEN,'MONTHLY P&L'!L28*(1+ASSUMPTION!$G$62)),'MONTHLY P&L'!L28) -> 0.25 | ... AO28: =IF(MOD(AO7,12)=4,MAX(ASSUMPTION!$G$56/DEN,'MONTHLY P&L'!AN28*(1+ASSUMPTION!$G$62)),'MONTHLY P&L'!AN28) -> 0.2916
A29: =ASSUMPTION!A57 -> Electricity (Based on area Rs./sq. Ft.) | F29: =IF(MOD(F8,12)=4,MAX((ASSUMPTION!$G$57*ASSUMPTION!$G$67)/DEN,'MONTHLY P&L'!E29*(1+ASSUMPTION!$G$62)),'MONTHLY P&L'!E29) -> 0 | G29: =IF(MOD(G8,12)=4,MAX((ASSUMPTION!$G$57*ASSUMPTION!$G$67)/DEN,'MONTHLY P&L'!F29*(1+ASSUMPTION!$G$62)),'MONTHLY P&L'!F29) -> 0 | H29: =IF(MOD(H8,12)=4,MAX((ASSUMPTION!$G$57*ASSUMPTION!$G$67)/DEN,'MONTHLY P&L'!G29*(1+ASSUMPTION!$G$62)),'MONTHLY P&L'!G29) -> 0 | I29: =IF(MOD(I7,12)=4,MAX((ASSUMPTION!$G$57*ASSUMPTION!$G$67)/DEN,'MONTHLY P&L'!H29*(1+ASSUMPTION!$G$62)),'MONTHLY P&L'!H29) -> 0.266 | J29: =IF(MOD(J8,12)=4,MAX((ASSUMPTION!$G$57*ASSUMPTION!$G$67)/DEN,'MONTHLY P&L'!I29*(1+ASSUMPTION!$G$62)),'MONTHLY P&L'!I29) -> 0.266 | K29: =IF(MOD(K8,12)=4,MAX((ASSUMPTION!$G$57*ASSUMPTION!$G$67)/DEN,'MONTHLY P&L'!J29*(1+ASSUMPTION!$G$62)),'MONTHLY P&L'!J29) -> 0.28728 | L29: =IF(MOD(L8,12)=4,MAX((ASSUMPTION!$G$57*ASSUMPTION!$G$67)/DEN,'MONTHLY P&L'!K29*(1+ASSUMPTION!$G$62)),'MONTHLY P&L'!K29) -> 0.28728 | M29: =IF(MOD(M8,12)=4,MAX((ASSUMPTION!$G$57*ASSUMPTION!$G$67)/DEN,'MONTHLY P&L'!L29*(1+ASSUMPTION!$G$62)),'MONTHLY P&L'!L29) -> 0.28728 | N29: =IF(MOD(N8,12)=4,MAX((ASSUMPTION!$G$57*ASSUMPTION!$G$67)/DEN,'MONTHLY P&L'!M29*(1+ASSUMPTION!$G$62)),'MONTHLY P&L'!M29) -> 0.28728 | O29: =IF(MOD(O8,12)=4,MAX((ASSUMPTION!$G$57*ASSUMPTION!$G$67)/DEN,'MONTHLY P&L'!N29*(1+ASSUMPTION!$G$62)),'MONTHLY P&L'!N29) -> 0.28728 | P29: =IF(MOD(P8,12)=4,MAX((ASSUMPTION!$G$57*ASSUMPTION!$G$67)/DEN,'MONTHLY P&L'!O29*(1+ASSUMPTION!$G$62)),'MONTHLY P&L'!O29) -> 0.28728 | Q29: =IF(MOD(Q8,12)=4,MAX((ASSUMPTION!$G$57*ASSUMPTION!$G$67)/DEN,'MONTHLY P&L'!P29*(1+ASSUMPTION!$G$62)),'MONTHLY P&L'!P29) -> 0.28728 | ... AO29: =IF(MOD(AO8,12)=4,MAX((ASSUMPTION!$G$57*ASSUMPTION!$G$67)/DEN,'MONTHLY P&L'!AN29*(1+ASSUMPTION!$G$62)),'MONTHLY P&L'!AN29) -> 0.36189006
A30: =ASSUMPTION!A58 -> Phone and internet (per month) | F30: =IF(MOD(F7,12)=4,MAX(ASSUMPTION!$G$58/DEN,'MONTHLY P&L'!E30*(1+ASSUMPTION!$G$62)),'MONTHLY P&L'!E30) -> 0 | G30: =IF(MOD(G7,12)=4,MAX(ASSUMPTION!$G$58/DEN,'MONTHLY P&L'!F30*(1+ASSUMPTION!$G$62)),'MONTHLY P&L'!F30) -> 0 | H30: =IF(MOD(H7,12)=4,MAX(ASSUMPTION!$G$58/DEN,'MONTHLY P&L'!G30*(1+ASSUMPTION!$G$62)),'MONTHLY P&L'!G30) -> 0 | I30: =IF(MOD(I7,12)=4,MAX(ASSUMPTION!$G$58/DEN,'MONTHLY P&L'!H30*(1+ASSUMPTION!$G$62)),'MONTHLY P&L'!H30) -> 0.15 | J30: =IF(MOD(J7,12)=4,MAX(ASSUMPTION!$G$58/DEN,'MONTHLY P&L'!I30*(1+ASSUMPTION!$G$62)),'MONTHLY P&L'!I30) -> 0.15 | K30: =IF(MOD(K7,12)=4,MAX(ASSUMPTION!$G$58/DEN,'MONTHLY P&L'!J30*(1+ASSUMPTION!$G$62)),'MONTHLY P&L'!J30) -> 0.15 | L30: =IF(MOD(L7,12)=4,MAX(ASSUMPTION!$G$58/DEN,'MONTHLY P&L'!K30*(1+ASSUMPTION!$G$62)),'MONTHLY P&L'!K30) -> 0.15 | M30: =IF(MOD(M7,12)=4,MAX(ASSUMPTION!$G$58/DEN,'MONTHLY P&L'!L30*(1+ASSUMPTION!$G$62)),'MONTHLY P&L'!L30) -> 0.15 | ... AO30: =IF(MOD(AO7,12)=4,MAX(ASSUMPTION!$G$58/DEN,'MONTHLY P&L'!AN30*(1+ASSUMPTION!$G$62)),'MONTHLY P&L'!AN30) -> 0.17496
A31: =ASSUMPTION!A59 -> Housekeeping & Consumables (% of revenue) | F31: =F13*ASSUMPTION!$G$59 -> 0 | G31: =G13*ASSUMPTION!$G$59 -> 0 | H31: =H13*ASSUMPTION!$G$59 -> 0 | I31: =I13*ASSUMPTION!$G$59 -> 0.49128 | J31: =J13*ASSUMPTION!$G$59 -> 0.5172304 | K31: =K13*ASSUMPTION!$G$59 -> 0.50290029 | L31: =L13*ASSUMPTION!$G$59 -> 0.53922819 | M31: =M13*ASSUMPTION!$G$59 -> 0.53861043 | ... AO31: =AO13*ASSUMPTION!$G$59 -> 1.2258612
A32: =ASSUMPTION!A60 -> Payment Settlement Charges (% or revenue) | F32: =F13*ASSUMPTION!$G$60 -> 0 | G32: =G13*ASSUMPTION!$G$60 -> 0 | H32: =H13*ASSUMPTION!$G$60 -> 0 | I32: =I13*ASSUMPTION!$G$60*ASSUMPTION!$G$61 -> 0.18423 | J32: =J13*ASSUMPTION!$G$60*ASSUMPTION!$G$61 -> 0.1939614 | K32: =K13*ASSUMPTION!$G$60*ASSUMPTION!$G$61 -> 0.18858761 | L32: =L13*ASSUMPTION!$G$60*ASSUMPTION!$G$61 -> 0.20221057 | M32: =M13*ASSUMPTION!$G$60*ASSUMPTION!$G$61 -> 0.20197891 | N32: =N13*ASSUMPTION!$G$60*ASSUMPTION!$G$61 -> 0.21024018 | O32: =O13*ASSUMPTION!$G$60*ASSUMPTION!$G$61 -> 0.22303505 | P32: =P13*ASSUMPTION!$G$60*ASSUMPTION!$G$61 -> 0.20327222 | ... AO32: =AO13*ASSUMPTION!$G$60*ASSUMPTION!$G$61 -> 0.45969797
A33: Total Indirect Expenses | F33: =SUM(F23:F32) -> 0 | G33: =SUM(G23:G32) -> 0 | H33: =SUM(H23:H32) -> 0 | I33: =SUM(I23:I32) -> 9.42611 | J33: =SUM(J23:J32) -> 9.6564198 | K33: =SUM(K23:K32) -> 9.5505201 | L33: =SUM(L23:L32) -> 9.8729302 | M33: =SUM(M23:M32) -> 9.8674476 | ... AO33: =SUM(AO23:AO32) -> 16.840129
A35: EBITDA | F35: =F13-F20-F33 -> 0 | G35: =G13-G20-G33 -> 0 | H35: =H13-H20-H33 -> 0 | I35: =I13-I20-I33 -> -2.72311 | J35: =J13-J20-J33 -> -2.0871438 | K35: =K13-K20-K33 -> -2.4577737 | L35: =L13-L20-L33 -> -1.5592572 | M35: =M13-M20-M33 -> -1.5764098 | ... AO35: =AO13-AO20-AO33 -> 12.958858
A37: EBITDA MARGIN % | F37: N/A | G37: N/A | H37: N/A | I37: =I35/I13 -> -0.11085776 | J37: =J35/J13 -> -0.080704607 | K37: =K35/K13 -> -0.097743975 | L37: =L35/L13 -> -0.057832924 | M37: =M35/M13 -> -0.058536176 | N37: =N35/N13 -> -0.036535967 | O37: =O35/O13 -> -0.0062876156 | P37: =P35/P13 -> -0.054993787 | ... AO37: =AO35/AO13 -> 0.21142455
A39: END OF SHEET

Sheet CAPITAL STRUCTURE
A1: ALL FINAL VALUES IN | B1: =CONVERTER!C1 -> LAKHS
C7: 0
C8: 43922
A9: FIXED ASSETS
A10: =ASSUMPTION!A79 -> Kitchen Equipments and cutlery | C10: =ASSUMPTION!$G$79*ASSUMPTION!$G$70/DEN -> 30
A11: =ASSUMPTION!A80 -> Refrigeration Equipments | C11: =ASSUMPTION!$G$80*ASSUMPTION!$G$70/DEN -> 50
A12: =ASSUMPTION!A81 -> Furniture & Fixtures | C12: =ASSUMPTION!$G$69*ASSUMPTION!$G$81/DEN -> 51
A13: =ASSUMPTION!A82 -> Restaurants Décor | C13: =ASSUMPTION!$G$69*ASSUMPTION!$G$82/DEN -> 60
A14: TOTAL | C14: =SUM(C10:C13) -> 191
A16: ADD: RENT DEPOSITS | C16: =ASSUMPTION!$G$83/DEN -> 10
A17: ADD:WORKING CAPITAL | C17: =ASSUMPTION!$G$87/DEN -> 24
A20: TOTAL FUNDS REQUIRED | C20: =C14+C16+C17 -> 225
A22: SOURCES OF FUNDS
A23: EQUITY CAPITAL | B23: =ASSUMPTION!G100 -> 1 | C23: =B23*C20 -> 225
A24: DEBT | B24: =ASSUMPTION!G101 -> 0 | C24: =B24*C20 -> 0
A26: TOTAL FUNDS CONTRIBUTED | C26: =C23+C24 -> 225
A28: END OF SHEET

Sheet FIXED ASSET SCHEDULE
A1: ALL FINAL VALUES IN | B1: =CONVERTER!C1 -> LAKHS
F5: 1 | G5: =F5+1 -> 2 | H5: =G5+1 -> 3
F6: =EOMONTH(ASSUMPTION!G3,11) -> 44286 | G6: =EOMONTH(F6,12) -> 44651 | H6: =EOMONTH(G6,12) -> 45016
A8: ='CAPITAL STRUCTURE'!A10 -> Kitchen Equipments and cutlery
A9: OPENING BALANCE | F9: 0 | G9: =F13 -> 26.634247 | H9: =G13 -> 22.63911
A10: ADD:PURCHASES | F10: ='CAPITAL STRUCTURE'!C10 -> 30 | G10: 0 | H10: 0
A11: LESS:SALES | F11: 0 | G11: 0 | H11: 0
A12: LESS:DEPRICIATION | F12: =(F9+F10-F11)*ASSUMPTION!$G$96*MIN(365,F$6-ASSUMPTION!$G$5)/365 -> 3.3657534 | G12: =(G9+G10-G11)*ASSUMPTION!$G$96*MIN(365,G$6-ASSUMPTION!$G$5)/365 -> 3.995137 | H12: =(H9+H10-H11)*ASSUMPTION!$G$96*MIN(365,H$6-ASSUMPTION!$G$5)/365 -> 3.3958664
A13: CLOSING BALANCE | F13: =F9+F10-F11-F12 -> 26.634247 | G13: =G9+G10-G11-G12 -> 22.63911 | H13: =H9+H10-H11-H12 -> 19.243243
A16: ='CAPITAL STRUCTURE'!A11 -> Refrigeration Equipments
A17: OPENING BALANCE | F17: 0 | G17: =F21 -> 44.390411 | H17: =G21 -> 37.731849
A18: ADD:PURCHASES | F18: ='CAPITAL STRUCTURE'!C11 -> 50 | G18: 0 | H18: 0
A19: LESS:SALES | F19: 0 | G19: 0 | H19: 0
A20: LESS:DEPRICIATION | F20: =(F17+F18-F19)*ASSUMPTION!$G$96*MIN(365,F$6-ASSUMPTION!$G$5)/365 -> 5.609589 | G20: =(G17+G18-G19)*ASSUMPTION!$G$96*MIN(365,G$6-ASSUMPTION!$G$5)/365 -> 6.6585616 | H20: =(H17+H18-H19)*ASSUMPTION!$G$96*MIN(365,H$6-ASSUMPTION!$G$5)/365 -> 5.6597774
A21: CLOSING BALANCE | F21: =F17+F18-F19-F20 -> 44.390411 | G21: =G17+G18-G19-G20 -> 37.731849 | H21: =H17+H18-H19-H20 -> 32.072072
A24: ='CAPITAL STRUCTURE'!A12 -> Furniture & Fixtures
A25: OPENING BALANCE | F25: 0 | G25: =F29 -> 47.185479 | H25: =G29 -> 42.466932
A26: ADD:PURCHASES | F26: ='CAPITAL STRUCTURE'!C12 -> 51
A27: LESS:SALES | F27: 0 | G27: 0 | H27: 0
A28: LESS:DEPRICIATION | F28: =(F25+F26-F27)*ASSUMPTION!$G$97*MIN(365,F$6-ASSUMPTION!$G$5)/365 -> 3.8145205 | G28: =(G25+G26-G27)*ASSUMPTION!$G$97*MIN(365,G$6-ASSUMPTION!$G$5)/365 -> 4.7185479 | H28: =(H25+H26-H27)*ASSUMPTION!$G$97*MIN(365,H$6-ASSUMPTION!$G$5)/365 -> 4.2466932
A29: CLOSING BALANCE | F29: =F25+F26-F27-F28 -> 47.185479 | G29: =G25+G26-G27-G28 -> 42.466932 | H29: =H25+H26-H27-H28 -> 38.220238
A32: ='CAPITAL STRUCTURE'!A13 -> Restaurants Décor
A33: OPENING BALANCE | F33: 0 | G33: =F37 -> 55.512329 | H33: =G37 -> 49.961096
A34: ADD:PURCHASES | F34: ='CAPITAL STRUCTURE'!C13 -> 60 | G34: 0 | H34: 0
A35: LESS:SALES | F35: 0 | G35: 0 | H35: 0
A36: LESS:DEPRICIATION | F36: =(F33+F34-F35)*ASSUMPTION!$G$97*MIN(365,F$6-ASSUMPTION!$G$5)/365 -> 4.4876712 | G36: =(G33+G34-G35)*ASSUMPTION!$G$97*MIN(365,G$6-ASSUMPTION!$G$5)/365 -> 5.5512329 | H36: =(H33+H34-H35)*ASSUMPTION!$G$97*MIN(365,H$6-ASSUMPTION!$G$5)/365 -> 4.9961096
A37: CLOSING BALANCE | F37: =F33+F34-F35-F36 -> 55.512329 | G37: =G33+G34-G35-G36 -> 49.961096 | H37: =H33+H34-H35-H36 -> 44.964986
A40: END OF SHEET

Sheet WORKING CAPITAL
A1: ALL FINAL VALUES IN | B1: =CONVERTER!C1 -> LAKHS
F5: 1 | G5: =F5+1 -> 2 | H5: =G5+1 -> 3
F6: =EOMONTH(ASSUMPTION!G3,11) -> 44286 | G6: =EOMONTH(F6,12) -> 44651 | H6: =EOMONTH(G6,12) -> 45016
A7: CURRENT ASSETS
A8: INVENTORY
A9: =ASSUMPTION!A89 -> Alcoholic Beverages | F9: ='MONTHLY P&L'!Q16/30*ASSUMPTION!$G89 -> 2.7922226 | G9: ='MONTHLY P&L'!AC16/30*ASSUMPTION!$G89 -> 4.1534533 | H9: ='MONTHLY P&L'!AO16/30*ASSUMPTION!$G89 -> 5.7836825
A10: =ASSUMPTION!A90 -> Non-Alcoholic Beverages | F10: ='MONTHLY P&L'!Q17/30*ASSUMPTION!$G90 -> 0.77393948 | G10: ='MONTHLY P&L'!AC17/30*ASSUMPTION!$G90 -> 1.1277936 | H10: ='MONTHLY P&L'!AO17/30*ASSUMPTION!$G90 -> 1.5584252
A11: =ASSUMPTION!A91 -> Food | F11: =('MONTHLY P&L'!Q18/30)*ASSUMPTION!$G91 -> 0.92636728 | G11: =('MONTHLY P&L'!AC18/30)*ASSUMPTION!$G91 -> 1.3407216 | H11: =('MONTHLY P&L'!AO18/30)*ASSUMPTION!$G91 -> 1.8488065
A12: TOTAL | F12: =SUM(F9:F11) -> 4.4925293 | G12: =SUM(G9:G11) -> 6.6219686 | H12: =SUM(H9:H11) -> 9.1909141
A14: CURRENT LIABILITIES
A15: CREDITOR FOR EXPENSES | F15: =SUMIF('MONTHLY P&L'!$F$8:$AO$8,'WORKING CAPITAL'!F$6,'MONTHLY P&L'!$F$33:$AO$33)/ASSUMPTION!$G$93*30 -> 10.478811 | G15: =SUMIF('MONTHLY P&L'!$F$8:$AO$8,'WORKING CAPITAL'!G$6,'MONTHLY P&L'!$F$33:$AO$33)/ASSUMPTION!$G$93*30 -> 13.385956 | H15: =SUMIF('MONTHLY P&L'!$F$8:$AO$8,'WORKING CAPITAL'!H$6,'MONTHLY P&L'!$F$33:$AO$33)/ASSUMPTION!$G$93*30 -> 16.840129
A16: CREDITOR FOR RAW MATERIAL
A17: ALCOHOLIC BEVERAGES | F17: =SUMIF('MONTHLY P&L'!$F$8:$AO$8,'WORKING CAPITAL'!F$6,'MONTHLY P&L'!$F16:$AO16)/ASSUMPTION!$G$92*30 -> 2.7922226 | G17: =SUMIF('MONTHLY P&L'!$F$8:$AO$8,'WORKING CAPITAL'!G$6,'MONTHLY P&L'!$F16:$AO16)/ASSUMPTION!$G$92*30 -> 4.1534533 | H17: =SUMIF('MONTHLY P&L'!$F$8:$AO$8,'WORKING CAPITAL'!H$6,'MONTHLY P&L'!$F16:$AO16)/ASSUMPTION!$G$92*30 -> 5.7836825
A18: NON ALCOHOLIC BEVERAGES | F18: =SUMIF('MONTHLY P&L'!$F$8:$AO$8,'WORKING CAPITAL'!F$6,'MONTHLY P&L'!$F17:$AO17)/ASSUMPTION!$G$92*30 -> 1.547879 | G18: =SUMIF('MONTHLY P&L'!$F$8:$AO$8,'WORKING CAPITAL'!G$6,'MONTHLY P&L'!$F17:$AO17)/ASSUMPTION!$G$92*30 -> 2.2555872 | H18: =SUMIF('MONTHLY P&L'!$F$8:$AO$8,'WORKING CAPITAL'!H$6,'MONTHLY P&L'!$F17:$AO17)/ASSUMPTION!$G$92*30 -> 3.1168504
A19: FOOD | F19: =SUMIF('MONTHLY P&L'!$F$8:$AO$8,'WORKING CAPITAL'!F$6,'MONTHLY P&L'!$F18:$AO18)/ASSUMPTION!$G$92*30 -> 5.5582037 | G19: =SUMIF('MONTHLY P&L'!$F$8:$AO$8,'WORKING CAPITAL'!G$6,'MONTHLY P&L'!$F18:$AO18)/ASSUMPTION!$G$92*30 -> 8.0443299 | H19: =SUMIF('MONTHLY P&L'!$F$8:$AO$8,'WORKING CAPITAL'!H$6,'MONTHLY P&L'!$F18:$AO18)/ASSUMPTION!$G$92*30 -> 11.092839
A20: TOTAL | F20: =SUM(F15:F19) -> 20.377116 | G20: =SUM(G15:G19) -> 27.839327 | H20: =SUM(H15:H19) -> 36.8335
A22: WORKING CAPITAL | F22: =F12-F20 -> -15.884587 | G22: =G12-G20 -> -21.217358 | H22: =H12-H20 -> -27.642586
A23: CHANGES IN WORKING CAPITAL | F23: =-(F22-E22) -> 15.884587 | G23: =-(G22-F22) -> 5.3327713 | H23: =-(H22-G22) -> 6.4252281
A25: END OF SHEET

Sheet ANNUAL P&L
A1: ALL FINAL VALUES IN | B1: =CONVERTER!C1 -> LAKHS
F5: 1 | G5: =F5+1 -> 2 | H5: =G5+1 -> 3
E6: =ASSUMPTION!G3 -> 43922 | F6: =EOMONTH(ASSUMPTION!G3,11) -> 44286 | G6: =EOMONTH(F6,12) -> 44651 | H6: =EOMONTH(G6,12) -> 45016
A7: REVENUE
A8: Alcoholic Beverages | F8: =SUMIFS('MONTHLY P&L'!$F10:$AO10,'MONTHLY P&L'!$F$8:$AO$8,">"&'ANNUAL P&L'!E$6,'MONTHLY P&L'!$F$8:$AO$8,"<="&'ANNUAL P&L'!F$6) -> 64.585172 | G8: =SUMIFS('MONTHLY P&L'!$F10:$AO10,'MONTHLY P&L'!$F$8:$AO$8,">"&'ANNUAL P&L'!F$6,'MONTHLY P&L'!$F$8:$AO$8,"<="&'ANNUAL P&L'!G$6) -> 121.87672 | H8: =SUMIFS('MONTHLY P&L'!$F10:$AO10,'MONTHLY P&L'!$F$8:$AO$8,">"&'ANNUAL P&L'!G$6,'MONTHLY P&L'!$F$8:$AO$8,"<="&'ANNUAL P&L'!H$6) -> 180.72179
A9: Non Alcoholic Beverages | F9: =SUMIFS('MONTHLY P&L'!$F11:$AO11,'MONTHLY P&L'!$F$8:$AO$8,">"&'ANNUAL P&L'!E$6,'MONTHLY P&L'!$F$8:$AO$8,"<="&'ANNUAL P&L'!F$6) -> 31.165448 | G9: =SUMIFS('MONTHLY P&L'!$F11:$AO11,'MONTHLY P&L'!$F$8:$AO$8,">"&'ANNUAL P&L'!F$6,'MONTHLY P&L'!$F$8:$AO$8,"<="&'ANNUAL P&L'!G$6) -> 57.732685 | H9: =SUMIFS('MONTHLY P&L'!$F11:$AO11,'MONTHLY P&L'!$F$8:$AO$8,">"&'ANNUAL P&L'!G$6,'MONTHLY P&L'!$F$8:$AO$8,"<="&'ANNUAL P&L'!H$6) -> 84.085991
A10: FOOD | F10: =SUMIFS('MONTHLY P&L'!$F12:$AO12,'MONTHLY P&L'!$F$8:$AO$8,">"&'ANNUAL P&L'!E$6,'MONTHLY P&L'!$F$8:$AO$8,"<="&'ANNUAL P&L'!F$6) -> 148.95966 | G10: =SUMIFS('MONTHLY P&L'!$F12:$AO12,'MONTHLY P&L'!$F$8:$AO$8,">"&'ANNUAL P&L'!F$6,'MONTHLY P&L'!$F$8:$AO$8,"<="&'ANNUAL P&L'!G$6) -> 274.24132 | H10: =SUMIFS('MONTHLY P&L'!$F12:$AO12,'MONTHLY P&L'!$F$8:$AO$8,">"&'ANNUAL P&L'!G$6,'MONTHLY P&L'!$F$8:$AO$8,"<="&'ANNUAL P&L'!H$6) -> 397.0635
A11: TOTAL | F11: =SUMIFS('MONTHLY P&L'!$F13:$AO13,'MONTHLY P&L'!$F$8:$AO$8,">"&'ANNUAL P&L'!E$6,'MONTHLY P&L'!$F$8:$AO$8,"<="&'ANNUAL P&L'!F$6) -> 244.71028 | G11: =SUMIFS('MONTHLY P&L'!$F13:$AO13,'MONTHLY P&L'!$F$8:$AO$8,">"&'ANNUAL P&L'!F$6,'MONTHLY P&L'!$F$8:$AO$8,"<="&'ANNUAL P&L'!G$6) -> 453.85072 | H11: =SUMIFS('MONTHLY P&L'!$F13:$AO13,'MONTHLY P&L'!$F$8:$AO$8,">"&'ANNUAL P&L'!G$6,'MONTHLY P&L'!$F$8:$AO$8,"<="&'ANNUAL P&L'!H$6) -> 661.87128
F12: =SUMIFS('MONTHLY P&L'!$F14:$AO14,'MONTHLY P&L'!$F$8:$AO$8,">"&'ANNUAL P&L'!E$6,'MONTHLY P&L'!$F$8:$AO$8,"<="&'ANNUAL P&L'!F$6) -> 0 | G12: =SUMIFS('MONTHLY P&L'!$F14:$AO14,'MONTHLY P&L'!$F$8:$AO$8,">"&'ANNUAL P&L'!F$6,'MONTHLY P&L'!$F$8:$AO$8,"<="&'ANNUAL P&L'!G$6) -> 0 | H12: =SUMIFS('MONTHLY P&L'!$F14:$AO14,'MONTHLY P&L'!$F$8:$AO$8,">"&'ANNUAL P&L'!G$6,'MONTHLY P&L'!$F$8:$AO$8,"<="&'ANNUAL P&L'!H$6) -> 0
A13: LESS:DIRECT EXPENSES | F13: =SUMIFS('MONTHLY P&L'!$F15:$AO15,'MONTHLY P&L'!$F$8:$AO$8,">"&'ANNUAL P&L'!E$6,'MONTHLY P&L'!$F$8:$AO$8,"<="&'ANNUAL P&L'!F$6) -> 0 | G13: =SUMIFS('MONTHLY P&L'!$F15:$AO15,'MONTHLY P&L'!$F$8:$AO$8,">"&'ANNUAL P&L'!F$6,'MONTHLY P&L'!$F$8:$AO$8,"<="&'ANNUAL P&L'!G$6) -> 0 | H13: =SUMIFS('MONTHLY P&L'!$F15:$AO15,'MONTHLY P&L'!$F$8:$AO$8,">"&'ANNUAL P&L'!G$6,'MONTHLY P&L'!$F$8:$AO$8,"<="&'ANNUAL P&L'!H$6) -> 0
A14: Alcoholic Beverage cost (% of revenue) | F14: =SUMIFS('MONTHLY P&L'!$F16:$AO16,'MONTHLY P&L'!$F$8:$AO$8,">"&'ANNUAL P&L'!E$6,'MONTHLY P&L'!$F$8:$AO$8,"<="&'ANNUAL P&L'!F$6) -> 22.60481 | G14: =SUMIFS('MONTHLY P&L'!$F16:$AO16,'MONTHLY P&L'!$F$8:$AO$8,">"&'ANNUAL P&L'!F$6,'MONTHLY P&L'!$F$8:$AO$8,"<="&'ANNUAL P&L'!G$6) -> 42.656851 | H14: =SUMIFS('MONTHLY P&L'!$F16:$AO16,'MONTHLY P&L'!$F$8:$AO$8,">"&'ANNUAL P&L'!G$6,'MONTHLY P&L'!$F$8:$AO$8,"<="&'ANNUAL P&L'!H$6) -> 63.252626
A15: Non Alcoholic Beverages (% of revenue) | F15: =SUMIFS('MONTHLY P&L'!$F17:$AO17,'MONTHLY P&L'!$F$8:$AO$8,">"&'ANNUAL P&L'!E$6,'MONTHLY P&L'!$F$8:$AO$8,"<="&'ANNUAL P&L'!F$6) -> 12.466179 | G15: =SUMIFS('MONTHLY P&L'!$F17:$AO17,'MONTHLY P&L'!$F$8:$AO$8,">"&'ANNUAL P&L'!F$6,'MONTHLY P&L'!$F$8:$AO$8,"<="&'ANNUAL P&L'!G$6) -> 23.093074 | H15: =SUMIFS('MONTHLY P&L'!$F17:$AO17,'MONTHLY P&L'!$F$8:$AO$8,">"&'ANNUAL P&L'!G$6,'MONTHLY P&L'!$F$8:$AO$8,"<="&'ANNUAL P&L'!H$6) -> 33.634396
A16: Food (% of revenue) | F16: =SUMIFS('MONTHLY P&L'!$F18:$AO18,'MONTHLY P&L'!$F$8:$AO$8,">"&'ANNUAL P&L'!E$6,'MONTHLY P&L'!$F$8:$AO$8,"<="&'ANNUAL P&L'!F$6) -> 44.687898 | G16: =SUMIFS('MONTHLY P&L'!$F18:$AO18,'MONTHLY P&L'!$F$8:$AO$8,">"&'ANNUAL P&L'!F$6,'MONTHLY P&L'!$F$8:$AO$8,"<="&'ANNUAL P&L'!G$6) -> 82.272396 | H16: =SUMIFS('MONTHLY P&L'!$F18:$AO18,'MONTHLY P&L'!$F$8:$AO$8,">"&'ANNUAL P&L'!G$6,'MONTHLY P&L'!$F$8:$AO$8,"<="&'ANNUAL P&L'!H$6) -> 119.11905
A17: Staff Salary | F17: =SUMIFS('MONTHLY P&L'!$F19:$AO19,'MONTHLY P&L'!$F$8:$AO$8,">"&'ANNUAL P&L'!E$6,'MONTHLY P&L'!$F$8:$AO$8,"<="&'ANNUAL P&L'!F$6) -> 88.74 | G17: =SUMIFS('MONTHLY P&L'!$F19:$AO19,'MONTHLY P&L'!$F$8:$AO$8,">"&'ANNUAL P&L'!F$6,'MONTHLY P&L'!$F$8:$AO$8,"<="&'ANNUAL P&L'!G$6) -> 125.4192 | H17: =SUMIFS('MONTHLY P&L'!$F19:$AO19,'MONTHLY P&L'!$F$8:$AO$8,">"&'ANNUAL P&L'!G$6,'MONTHLY P&L'!$F$8:$AO$8,"<="&'ANNUAL P&L'!H$6) -> 135.45274
A18: Total Direct Expenses | F18: =SUMIFS('MONTHLY P&L'!$F20:$AO20,'MONTHLY P&L'!$F$8:$AO$8,">"&'ANNUAL P&L'!E$6,'MONTHLY P&L'!$F$8:$AO$8,"<="&'ANNUAL P&L'!F$6) -> 168.49889 | G18: =SUMIFS('MONTHLY P&L'!$F20:$AO20,'MONTHLY P&L'!$F$8:$AO$8,">"&'ANNUAL P&L'!F$6,'MONTHLY P&L'!$F$8:$AO$8,"<="&'ANNUAL P&L'!G$6) -> 273.44152 | H18: =SUMIFS('MONTHLY P&L'!$F20:$AO20,'MONTHLY P&L'!$F$8:$AO$8,">"&'ANNUAL P&L'!G$6,'MONTHLY P&L'!$F$8:$AO$8,"<="&'ANNUAL P&L'!H$6) -> 351.45881
F19: =SUMIFS('MONTHLY P&L'!$F21:$AO21,'MONTHLY P&L'!$F$8:$AO$8,">"&'ANNUAL P&L'!E$6,'MONTHLY P&L'!$F$8:$AO$8,"<="&'ANNUAL P&L'!F$6) -> 0 | G19: =SUMIFS('MONTHLY P&L'!$F21:$AO21,'MONTHLY P&L'!$F$8:$AO$8,">"&'ANNUAL P&L'!F$6,'MONTHLY P&L'!$F$8:$AO$8,"<="&'ANNUAL P&L'!G$6) -> 0 | H19: =SUMIFS('MONTHLY P&L'!$F21:$AO21,'MONTHLY P&L'!$F$8:$AO$8,">"&'ANNUAL P&L'!G$6,'MONTHLY P&L'!$F$8:$AO$8,"<="&'ANNUAL P&L'!H$6) -> 0
A20: LESS:INDIRECT EXPENSES | F20: =SUMIFS('MONTHLY P&L'!$F22:$AO22,'MONTHLY P&L'!$F$8:$AO$8,">"&'ANNUAL P&L'!E$6,'MONTHLY P&L'!$F$8:$AO$8,"<="&'ANNUAL P&L'!F$6) -> 0 | G20: =SUMIFS('MONTHLY P&L'!$F22:$AO22,'MONTHLY P&L'!$F$8:$AO$8,">"&'ANNUAL P&L'!F$6,'MONTHLY P&L'!$F$8:$AO$8,"<="&'ANNUAL P&L'!G$6) -> 0 | H20: =SUMIFS('MONTHLY P&L'!$F22:$AO22,'MONTHLY P&L'!$F$8:$AO$8,">"&'ANNUAL P&L'!G$6,'MONTHLY P&L'!$F$8:$AO$8,"<="&'ANNUAL P&L'!H$6) -> 0
A21: OTHER STAFF SALARY | F21: =SUMIFS('MONTHLY P&L'!$F23:$AO23,'MONTHLY P&L'!$F$8:$AO$8,">"&'ANNUAL P&L'!E$6,'MONTHLY P&L'!$F$8:$AO$8,"<="&'ANNUAL P&L'!F$6) -> 34.2 | G21: =SUMIFS('MONTHLY P&L'!$F23:$AO23,'MONTHLY P&L'!$F$8:$AO$8,">"&'ANNUAL P&L'!F$6,'MONTHLY P&L'!$F$8:$AO$8,"<="&'ANNUAL P&L'!G$6) -> 48.336 | H21: =SUMIFS('MONTHLY P&L'!$F23:$AO23,'MONTHLY P&L'!$F$8:$AO$8,">"&'ANNUAL P&L'!G$6,'MONTHLY P&L'!$F$8:$AO$8,"<="&'ANNUAL P&L'!H$6) -> 52.20288
A22: Rotalty to brand (% Of Revenue) | F22: =SUMIFS('MONTHLY P&L'!$F24:$AO24,'MONTHLY P&L'!$F$8:$AO$8,">"&'ANNUAL P&L'!E$6,'MONTHLY P&L'!$F$8:$AO$8,"<="&'ANNUAL P&L'!F$6) -> 12.235514 | G22: =SUMIFS('MONTHLY P&L'!$F24:$AO24,'MONTHLY P&L'!$F$8:$AO$8,">"&'ANNUAL P&L'!F$6,'MONTHLY P&L'!$F$8:$AO$8,"<="&'ANNUAL P&L'!G$6) -> 22.692536 | H22: =SUMIFS('MONTHLY P&L'!$F24:$AO24,'MONTHLY P&L'!$F$8:$AO$8,">"&'ANNUAL P&L'!G$6,'MONTHLY P&L'!$F$8:$AO$8,"<="&'ANNUAL P&L'!H$6) -> 33.093564
A23: Rent (as per contract) (% of revenue) | F23: =SUMIFS('MONTHLY P&L'!$F25:$AO25,'MONTHLY P&L'!$F$8:$AO$8,">"&'ANNUAL P&L'!E$6,'MONTHLY P&L'!$F$8:$AO$8,"<="&'ANNUAL P&L'!F$6) -> 24.471028 | G23: =SUMIFS('MONTHLY P&L'!$F25:$AO25,'MONTHLY P&L'!$F$8:$AO$8,">"&'ANNUAL P&L'!F$6,'MONTHLY P&L'!$F$8:$AO$8,"<="&'ANNUAL P&L'!G$6) -> 45.385072 | H23: =SUMIFS('MONTHLY P&L'!$F25:$AO25,'MONTHLY P&L'!$F$8:$AO$8,">"&'ANNUAL P&L'!G$6,'MONTHLY P&L'!$F$8:$AO$8,"<="&'ANNUAL P&L'!H$6) -> 66.187128
A24: Water Cost (per month) | F24: =SUMIFS('MONTHLY P&L'!$F26:$AO26,'MONTHLY P&L'!$F$8:$AO$8,">"&'ANNUAL P&L'!E$6,'MONTHLY P&L'!$F$8:$AO$8,"<="&'ANNUAL P&L'!F$6) -> 0.9 | G24: =SUMIFS('MONTHLY P&L'!$F26:$AO26,'MONTHLY P&L'!$F$8:$AO$8,">"&'ANNUAL P&L'!F$6,'MONTHLY P&L'!$F$8:$AO$8,"<="&'ANNUAL P&L'!G$6) -> 1.272 | H24: =SUMIFS('MONTHLY P&L'!$F26:$AO26,'MONTHLY P&L'!$F$8:$AO$8,">"&'ANNUAL P&L'!G$6,'MONTHLY P&L'!$F$8:$AO$8,"<="&'ANNUAL P&L'!H$6) -> 1.37376
A25: Maintenance (per month) | F25: =SUMIFS('MONTHLY P&L'!$F27:$AO27,'MONTHLY P&L'!$F$8:$AO$8,">"&'ANNUAL P&L'!E$6,'MONTHLY P&L'!$F$8:$AO$8,"<="&'ANNUAL P&L'!F$6) -> 4.5 | G25: =SUMIFS('MONTHLY P&L'!$F27:$AO27,'MONTHLY P&L'!$F$8:$AO$8,">"&'ANNUAL P&L'!F$6,'MONTHLY P&L'!$F$8:$AO$8,"<="&'ANNUAL P&L'!G$6) -> 6.36 | H25: =SUMIFS('MONTHLY P&L'!$F27:$AO27,'MONTHLY P&L'!$F$8:$AO$8,">"&'ANNUAL P&L'!G$6,'MONTHLY P&L'!$F$8:$AO$8,"<="&'ANNUAL P&L'!H$6) -> 6.8688
A26: Marketing cost (per month) | F26: =SUMIFS('MONTHLY P&L'!$F28:$AO28,'MONTHLY P&L'!$F$8:$AO$8,">"&'ANNUAL P&L'!E$6,'MONTHLY P&L'!$F$8:$AO$8,"<="&'ANNUAL P&L'!F$6) -> 2.25 | G26: =SUMIFS('MONTHLY P&L'!$F28:$AO28,'MONTHLY P&L'!$F$8:$AO$8,">"&'ANNUAL P&L'!F$6,'MONTHLY P&L'!$F$8:$AO$8,"<="&'ANNUAL P&L'!G$6) -> 3.18 | H26: =SUMIFS('MONTHLY P&L'!$F28:$AO28,'MONTHLY P&L'!$F$8:$AO$8,">"&'ANNUAL P&L'!G$6,'MONTHLY P&L'!$F$8:$AO$8,"<="&'ANNUAL P&L'!H$6) -> 3.4344
A27: Electricity (Based on area Rs./sq. Ft.) | F27: =SUMIFS('MONTHLY P&L'!$F29:$AO29,'MONTHLY P&L'!$F$8:$AO$8,">"&'ANNUAL P&L'!E$6,'MONTHLY P&L'!$F$8:$AO$8,"<="&'ANNUAL P&L'!F$6) -> 2.54296 | G27: =SUMIFS('MONTHLY P&L'!$F29:$AO29,'MONTHLY P&L'!$F$8:$AO$8,">"&'ANNUAL P&L'!F$6,'MONTHLY P&L'!$F$8:$AO$8,"<="&'ANNUAL P&L'!G$6) -> 3.6348964 | H27: =SUMIFS('MONTHLY P&L'!$F29:$AO29,'MONTHLY P&L'!$F$8:$AO$8,">"&'ANNUAL P&L'!G$6,'MONTHLY P&L'!$F$8:$AO$8,"<="&'ANNUAL P&L'!H$6) -> 4.0478074
A28: Phone and internet (per month) | F28: =SUMIFS('MONTHLY P&L'!$F30:$AO30,'MONTHLY P&L'!$F$8:$AO$8,">"&'ANNUAL P&L'!E$6,'MONTHLY P&L'!$F$8:$AO$8,"<="&'ANNUAL P&L'!F$6) -> 1.35 | G28: =SUMIFS('MONTHLY P&L'!$F30:$AO30,'MONTHLY P&L'!$F$8:$AO$8,">"&'ANNUAL P&L'!F$6,'MONTHLY P&L'!$F$8:$AO$8,"<="&'ANNUAL P&L'!G$6) -> 1.908 | H28: =SUMIFS('MONTHLY P&L'!$F30:$AO30,'MONTHLY P&L'!$F$8:$AO$8,">"&'ANNUAL P&L'!G$6,'MONTHLY P&L'!$F$8:$AO$8,"<="&'ANNUAL P&L'!H$6) -> 2.06064
A29: Housekeeping & Consumables (% of revenue) | F29: =SUMIFS('MONTHLY P&L'!$F31:$AO31,'MONTHLY P&L'!$F$8:$AO$8,">"&'ANNUAL P&L'!E$6,'MONTHLY P&L'!$F$8:$AO$8,"<="&'ANNUAL P&L'!F$6) -> 4.8942056 | G29: =SUMIFS('MONTHLY P&L'!$F31:$AO31,'MONTHLY P&L'!$F$8:$AO$8,">"&'ANNUAL P&L'!F$6,'MONTHLY P&L'!$F$8:$AO$8,"<="&'ANNUAL P&L'!G$6) -> 9.0770144 | H29: =SUMIFS('MONTHLY P&L'!$F31:$AO31,'MONTHLY P&L'!$F$8:$AO$8,">"&'ANNUAL P&L'!G$6,'MONTHLY P&L'!$F$8:$AO$8,"<="&'ANNUAL P&L'!H$6) -> 13.237426
A30: Payment Settlement Charges (% or revenue) | F30: =SUMIFS('MONTHLY P&L'!$F32:$AO32,'MONTHLY P&L'!$F$8:$AO$8,">"&'ANNUAL P&L'!E$6,'MONTHLY P&L'!$F$8:$AO$8,"<="&'ANNUAL P&L'!F$6) -> 1.8353271 | G30: =SUMIFS('MONTHLY P&L'!$F32:$AO32,'MONTHLY P&L'!$F$8:$AO$8,">"&'ANNUAL P&L'!F$6,'MONTHLY P&L'!$F$8:$AO$8,"<="&'ANNUAL P&L'!G$6) -> 3.4038804 | H30: =SUMIFS('MONTHLY P&L'!$F32:$AO32,'MONTHLY P&L'!$F$8:$AO$8,">"&'ANNUAL P&L'!G$6,'MONTHLY P&L'!$F$8:$AO$8,"<="&'ANNUAL P&L'!H$6) -> 4.9640346
A31: Total Indirect Expenses | F31: =SUMIFS('MONTHLY P&L'!$F33:$AO33,'MONTHLY P&L'!$F$8:$AO$8,">"&'ANNUAL P&L'!E$6,'MONTHLY P&L'!$F$8:$AO$8,"<="&'ANNUAL P&L'!F$6) -> 89.179035 | G31: =SUMIFS('MONTHLY P&L'!$F33:$AO33,'MONTHLY P&L'!$F$8:$AO$8,">"&'ANNUAL P&L'!F$6,'MONTHLY P&L'!$F$8:$AO$8,"<="&'ANNUAL P&L'!G$6) -> 145.2494 | H31: =SUMIFS('MONTHLY P&L'!$F33:$AO33,'MONTHLY P&L'!$F$8:$AO$8,">"&'ANNUAL P&L'!G$6,'MONTHLY P&L'!$F$8:$AO$8,"<="&'ANNUAL P&L'!H$6) -> 187.47044
F32: =SUMIFS('MONTHLY P&L'!$F34:$AO34,'MONTHLY P&L'!$F$8:$AO$8,">"&'ANNUAL P&L'!E$6,'MONTHLY P&L'!$F$8:$AO$8,"<="&'ANNUAL P&L'!F$6) -> 0 | G32: =SUMIFS('MONTHLY P&L'!$F34:$AO34,'MONTHLY P&L'!$F$8:$AO$8,">"&'ANNUAL P&L'!F$6,'MONTHLY P&L'!$F$8:$AO$8,"<="&'ANNUAL P&L'!G$6) -> 0 | H32: =SUMIFS('MONTHLY P&L'!$F34:$AO34,'MONTHLY P&L'!$F$8:$AO$8,">"&'ANNUAL P&L'!G$6,'MONTHLY P&L'!$F$8:$AO$8,"<="&'ANNUAL P&L'!H$6) -> 0
A33: EBITDA | F33: =SUMIFS('MONTHLY P&L'!$F35:$AO35,'MONTHLY P&L'!$F$8:$AO$8,">"&'ANNUAL P&L'!E$6,'MONTHLY P&L'!$F$8:$AO$8,"<="&'ANNUAL P&L'!F$6) -> -12.967642 | G33: =SUMIFS('MONTHLY P&L'!$F35:$AO35,'MONTHLY P&L'!$F$8:$AO$8,">"&'ANNUAL P&L'!F$6,'MONTHLY P&L'!$F$8:$AO$8,"<="&'ANNUAL P&L'!G$6) -> 35.159802 | H33: =SUMIFS('MONTHLY P&L'!$F35:$AO35,'MONTHLY P&L'!$F$8:$AO$8,">"&'ANNUAL P&L'!G$6,'MONTHLY P&L'!$F$8:$AO$8,"<="&'ANNUAL P&L'!H$6) -> 122.94203
A34: LESS:DEPRICIATION | F34: =SUM('FIXED ASSET SCHEDULE'!F12,'FIXED ASSET SCHEDULE'!F20,'FIXED ASSET SCHEDULE'!F28,'FIXED ASSET SCHEDULE'!F36) -> 17.277534 | G34: =SUM('FIXED ASSET SCHEDULE'!G12,'FIXED ASSET SCHEDULE'!G20,'FIXED ASSET SCHEDULE'!G28,'FIXED ASSET SCHEDULE'!G36) -> 20.923479 | H34: =SUM('FIXED ASSET SCHEDULE'!H12,'FIXED ASSET SCHEDULE'!H20,'FIXED ASSET SCHEDULE'!H28,'FIXED ASSET SCHEDULE'!H36) -> 18.298447
A36: EBIT | F36: =F33-F34 -> -30.245176 | G36: =G33-G34 -> 14.236322 | H36: =H33-H34 -> 104.64359
A37: LESS:INTEREST | F37: 0 | G37: 0 | H37: 0
A39: EBT | F39: =F36-F37 -> -30.245176 | G39: =G36-G37 -> 14.236322 | H39: =H36-H37 -> 104.64359
A40: LESS:TAXES | F40: =IF(F$39>0,F$39*ASSUMPTION!$G$105,0) -> 0 | G40: =IF(G$39>0,G$39*ASSUMPTION!$G$105,0) -> 3.5832823 | H40: =IF(H$39>0,H$39*ASSUMPTION!$G$105,0) -> 26.33879
A42: EAT | F42: =F39-F40 -> -30.245176 | G42: =G39-G40 -> 10.65304 | H42: =H39-H40 -> 78.304795
A44: NP MARGIN% | F44: =F42/F11 -> -0.12359585 | G44: =G42/G11 -> 0.023472564 | H44: =H42/H11 -> 0.11830819
A46: END OF SHEET

Sheet BALANCE SHEET
A1: ALL FINAL VALUES IN | B1: =CONVERTER!C1 -> LAKHS
F5: 1 | G5: =F5+1 -> 2 | H5: =G5+1 -> 3
F6: =EOMONTH(ASSUMPTION!G3,11) -> 44286 | G6: =EOMONTH(F6,12) -> 44651 | H6: =EOMONTH(G6,12) -> 45016
A7: EQUITY AND LIABILITY
A8: SHARE CAPITAL | F8: ='CAPITAL STRUCTURE'!C23 -> 225 | G8: =F8 -> 225 | H8: =G8 -> 225
A9: RESERVES AND SURPLUS | F9: ='ANNUAL P&L'!F42 -> -30.245176 | G9: =F9+'ANNUAL P&L'!G42 -> -19.592136 | H9: =G9+'ANNUAL P&L'!H42 -> 58.712659
A11: TOTAL SHAREHOLDERS FUND | F11: =SUM(F8:F10) -> 194.75482 | G11: =SUM(G8:G10) -> 205.40786 | H11: =SUM(H8:H10) -> 283.71266
A13: CURRENT LIABILITIES
A14: ='WORKING CAPITAL'!A15 -> CREDITOR FOR EXPENSES | F14: ='WORKING CAPITAL'!F15 -> 10.478811 | G14: ='WORKING CAPITAL'!G15 -> 13.385956 | H14: ='WORKING CAPITAL'!H15 -> 16.840129
A15: ='WORKING CAPITAL'!A16 -> CREDITOR FOR RAW MATERIAL
A16: ='WORKING CAPITAL'!A17 -> ALCOHOLIC BEVERAGES | F16: ='WORKING CAPITAL'!F17 -> 2.7922226 | G16: ='WORKING CAPITAL'!G17 -> 4.1534533 | H16: ='WORKING CAPITAL'!H17 -> 5.7836825
A17: ='WORKING CAPITAL'!A18 -> NON ALCOHOLIC BEVERAGES | F17: ='WORKING CAPITAL'!F18 -> 1.547879 | G17: ='WORKING CAPITAL'!G18 -> 2.2555872 | H17: ='WORKING CAPITAL'!H18 -> 3.1168504
A18: ='WORKING CAPITAL'!A19 -> FOOD | F18: ='WORKING CAPITAL'!F19 -> 5.5582037 | G18: ='WORKING CAPITAL'!G19 -> 8.0443299 | H18: ='WORKING CAPITAL'!H19 -> 11.092839
A19: TOTAL CURRENT LIABILITIES | F19: ='WORKING CAPITAL'!F20 -> 20.377116 | G19: ='WORKING CAPITAL'!G20 -> 27.839327 | H19: ='WORKING CAPITAL'!H20 -> 36.8335
A21: TOTAL LIABILITIES | F21: =F11+F19 -> 215.13194 | G21: =G11+G19 -> 233.24719 | H21: =H11+H19 -> 320.54616
A24: ASSETS
A25: FIXED ASSETS
A26: ='FIXED ASSET SCHEDULE'!A8 -> Kitchen Equipments and cutlery | F26: ='FIXED ASSET SCHEDULE'!F13 -> 26.634247 | G26: ='FIXED ASSET SCHEDULE'!G13 -> 22.63911 | H26: ='FIXED ASSET SCHEDULE'!H13 -> 19.243243
A27: ='FIXED ASSET SCHEDULE'!A16 -> Refrigeration Equipments | F27: ='FIXED ASSET SCHEDULE'!F21 -> 44.390411 | G27: ='FIXED ASSET SCHEDULE'!G21 -> 37.731849 | H27: ='FIXED ASSET SCHEDULE'!H21 -> 32.072072
A28: ='FIXED ASSET SCHEDULE'!A24 -> Furniture & Fixtures | F28: ='FIXED ASSET SCHEDULE'!F29 -> 47.185479 | G28: ='FIXED ASSET SCHEDULE'!G29 -> 42.466932 | H28: ='FIXED ASSET SCHEDULE'!H29 -> 38.220238
A29: ='FIXED ASSET SCHEDULE'!A32 -> Restaurants Décor | F29: ='FIXED ASSET SCHEDULE'!F37 -> 55.512329 | G29: ='FIXED ASSET SCHEDULE'!G37 -> 49.961096 | H29: ='FIXED ASSET SCHEDULE'!H37 -> 44.964986
A31: RENT DEPOSITS | F31: ='CAPITAL STRUCTURE'!C16 -> 10 | G31: =F31 -> 10 | H31: =G31 -> 10
A33: CURRENT ASSETS
A34: INVENTORY
A35: ='WORKING CAPITAL'!A9 -> Alcoholic Beverages | F35: ='WORKING CAPITAL'!F9 -> 2.7922226 | G35: ='WORKING CAPITAL'!G9 -> 4.1534533 | H35: ='WORKING CAPITAL'!H9 -> 5.7836825
A36: ='WORKING CAPITAL'!A10 -> Non-Alcoholic Beverages | F36: ='WORKING CAPITAL'!F10 -> 0.77393948 | G36: ='WORKING CAPITAL'!G10 -> 1.1277936 | H36: ='WORKING CAPITAL'!H10 -> 1.5584252
A37: ='WORKING CAPITAL'!A11 -> Food | F37: ='WORKING CAPITAL'!F11 -> 0.92636728 | G37: ='WORKING CAPITAL'!G11 -> 1.3407216 | H37: ='WORKING CAPITAL'!H11 -> 1.8488065
A38: TOTAL | F38: ='WORKING CAPITAL'!F12 -> 4.4925293 | G38: ='WORKING CAPITAL'!G12 -> 6.6219686 | H38: ='WORKING CAPITAL'!H12 -> 9.1909141
A39: CASH AND CASH EQUIVALENTS | F39: ='CASHFLOW STATEMENT'!F26 -> 26.916945 | G39: ='CASHFLOW STATEMENT'!G26 -> 63.826236 | H39: ='CASHFLOW STATEMENT'!H26 -> 166.85471
A41: TOTAL ASSETS | F41: =SUM(F26:F29,F31,F38,F39) -> 215.13194 | G41: =SUM(G26:G29,G31,G38,G39) -> 233.24719 | H41: =SUM(H26:H29,H31,H38,H39) -> 320.54616
A43: CHECK | F43: =F21-F41 -> 0 | G43: =G21-G41 -> 0 | H43: =H21-H41 -> 0
A45: END OF SHEET

Sheet CASHFLOW STATEMENT
A1: ALL FINAL VALUES IN | B1: =CONVERTER!C1 -> LAKHS
F5: 1 | G5: =F5+1 -> 2 | H5: =G5+1 -> 3
F6: =EOMONTH(ASSUMPTION!G3,11) -> 44286 | G6: =EOMONTH(F6,12) -> 44651 | H6: =EOMONTH(G6,12) -> 45016
A7: OPERATING ACTIVITIES
A8: EAT | F8: ='ANNUAL P&L'!F42 -> -30.245176 | G8: ='ANNUAL P&L'!G42 -> 10.65304 | H8: ='ANNUAL P&L'!H42 -> 78.304795
A9: ADD:NON CASH EXPENSES | F9: ='ANNUAL P&L'!F34 -> 17.277534 | G9: ='ANNUAL P&L'!G34 -> 20.923479 | H9: ='ANNUAL P&L'!H34 -> 18.298447
A10: CASH FROM OPERATIONS BEFORE WORKING CAPITAL CHANGES | F10: =F8+F9 -> -12.967642 | G10: =G8+G9 -> 31.576519 | H10: =H8+H9 -> 96.603241
A11: ADD/LESS:CHANGES IN WORKING CAPITAL | F11: ='WORKING CAPITAL'!F23 -> 15.884587 | G11: ='WORKING CAPITAL'!G23 -> 5.3327713 | H11: ='WORKING CAPITAL'!H23 -> 6.4252281
A13: CASH FROM OPERATIONS | F13: =F10+F11 -> 2.9169452 | G13: =G10+G11 -> 36.909291 | H13: =H10+H11 -> 103.02847
A15: INVESTING ACTIVITIES
A16: PURCHASE OF FIXED ASSET | F16: =-'CAPITAL STRUCTURE'!C14 -> -191 | G16: 0 | H16: 0
A17: RENT DEPOSIT | F17: =-'CAPITAL STRUCTURE'!C16 -> -10 | G17: 0 | H17: 0
A18: CASH FROM INVESTING ACTIVITIES | F18: =F16+F17 -> -201 | G18: =G16+G17 -> 0 | H18: =H16+H17 -> 0
A20: FIINANCING ACTIVITIES
A21: EQUITY SHARE CAPITAL | F21: ='CAPITAL STRUCTURE'!C23 -> 225 | G21: 0 | H21: 0
A22: CASH FROM FINANCING ACTIVITIES | F22: =F21 -> 225 | G22: =G21 -> 0 | H22: =H21 -> 0
A24: CASH GENERATED DURING THE YEAR | F24: =F13+F18+F22 -> 26.916945 | G24: =G13+G18+G22 -> 36.909291 | H24: =H13+H18+H22 -> 103.02847
A25: ADD: OPENING BALANCE | F25: 0 | G25: =F26 -> 26.916945 | H25: =G26 -> 63.826236
A26: CLOSING BALANCE | F26: =F24+F25 -> 26.916945 | G26: =G24+G25 -> 63.826236 | H26: =H24+H25 -> 166.85471
A28: END OF SHEET
